{
"meta":{"test_sets":[],"test_metrics":[],"learn_metrics":[{"best_value":"Min","name":"RMSE"}],"launch_mode":"Train","parameters":"","iteration_count":1000,"learn_sets":["learn"],"name":"experiment"},
"iterations":[
{"learn":[14.61268541],"iteration":0,"passed_time":0.1411060742,"remaining_time":140.9649682},
{"learn":[14.23196558],"iteration":1,"passed_time":0.1441354561,"remaining_time":71.92359261},
{"learn":[13.86674177],"iteration":2,"passed_time":0.1472649264,"remaining_time":48.94104386},
{"learn":[13.49946468],"iteration":3,"passed_time":0.1502303696,"remaining_time":37.40736203},
{"learn":[13.16661202],"iteration":4,"passed_time":0.1532793521,"remaining_time":30.50259107},
{"learn":[12.85632158],"iteration":5,"passed_time":0.1563395201,"remaining_time":25.90024717},
{"learn":[12.56784336],"iteration":6,"passed_time":0.1593374837,"remaining_time":22.60316018},
{"learn":[12.31617801],"iteration":7,"passed_time":0.1623961507,"remaining_time":20.13712269},
{"learn":[12.01509946],"iteration":8,"passed_time":0.1655737302,"remaining_time":18.2315074},
{"learn":[11.71512571],"iteration":9,"passed_time":0.1685403891,"remaining_time":16.68549852},
{"learn":[11.43264457],"iteration":10,"passed_time":0.171823747,"remaining_time":15.44851689},
{"learn":[11.17973129],"iteration":11,"passed_time":0.1750304362,"remaining_time":14.41083925},
{"learn":[10.93746433],"iteration":12,"passed_time":0.1781420407,"remaining_time":13.52509186},
{"learn":[10.69387075],"iteration":13,"passed_time":0.1812662588,"remaining_time":12.76632366},
{"learn":[10.4615922],"iteration":14,"passed_time":0.184327136,"remaining_time":12.1041486},
{"learn":[10.2299235],"iteration":15,"passed_time":0.1873601073,"remaining_time":11.5226466},
{"learn":[10.01419731],"iteration":16,"passed_time":0.1903768388,"remaining_time":11.00826074},
{"learn":[9.795856918],"iteration":17,"passed_time":0.1936289931,"remaining_time":10.56353729},
{"learn":[9.60040151],"iteration":18,"passed_time":0.1966614434,"remaining_time":10.15394084},
{"learn":[9.418664989],"iteration":19,"passed_time":0.199721448,"remaining_time":9.78635095},
{"learn":[9.249278645],"iteration":20,"passed_time":0.202766737,"remaining_time":9.452792168},
{"learn":[9.090113396],"iteration":21,"passed_time":0.2057638446,"remaining_time":9.147138185},
{"learn":[8.909548708],"iteration":22,"passed_time":0.2090418038,"remaining_time":8.879732273},
{"learn":[8.740140208],"iteration":23,"passed_time":0.2119672139,"remaining_time":8.620000032},
{"learn":[8.59377682],"iteration":24,"passed_time":0.2150150906,"remaining_time":8.385588532},
{"learn":[8.453885414],"iteration":25,"passed_time":0.2180535744,"remaining_time":8.168622364},
{"learn":[8.317732234],"iteration":26,"passed_time":0.2210076166,"remaining_time":7.964459664},
{"learn":[8.180896085],"iteration":27,"passed_time":0.2248972843,"remaining_time":7.807148585},
{"learn":[8.053220863],"iteration":28,"passed_time":0.2279152059,"remaining_time":7.631229825},
{"learn":[7.924234474],"iteration":29,"passed_time":0.2309359987,"remaining_time":7.466930626},
{"learn":[7.818879511],"iteration":30,"passed_time":0.234014615,"remaining_time":7.314843934},
{"learn":[7.719346395],"iteration":31,"passed_time":0.2369912638,"remaining_time":7.168985729},
{"learn":[7.624163594],"iteration":32,"passed_time":0.2400399578,"remaining_time":7.033898158},
{"learn":[7.524952543],"iteration":33,"passed_time":0.2430997179,"remaining_time":6.906891986},
{"learn":[7.424464745],"iteration":34,"passed_time":0.2460857916,"remaining_time":6.784936825},
{"learn":[7.327482321],"iteration":35,"passed_time":0.2490847175,"remaining_time":6.669935213},
{"learn":[7.238666841],"iteration":36,"passed_time":0.2522177875,"remaining_time":6.564479172},
{"learn":[7.158842395],"iteration":37,"passed_time":0.2552392166,"remaining_time":6.461582273},
{"learn":[7.074348246],"iteration":38,"passed_time":0.2581936018,"remaining_time":6.362155162},
{"learn":[6.992269093],"iteration":39,"passed_time":0.2611433943,"remaining_time":6.267441464},
{"learn":[6.925219745],"iteration":40,"passed_time":0.2641512679,"remaining_time":6.178562584},
{"learn":[6.86013671],"iteration":41,"passed_time":0.2672805066,"remaining_time":6.096541078},
{"learn":[6.786739622],"iteration":42,"passed_time":0.2702599505,"remaining_time":6.014855177},
{"learn":[6.73057926],"iteration":43,"passed_time":0.2732813372,"remaining_time":5.937658144},
{"learn":[6.666356486],"iteration":44,"passed_time":0.2762522497,"remaining_time":5.862686633},
{"learn":[6.606182832],"iteration":45,"passed_time":0.2794542837,"remaining_time":5.795638841},
{"learn":[6.547854615],"iteration":46,"passed_time":0.2825427176,"remaining_time":5.729004464},
{"learn":[6.49240675],"iteration":47,"passed_time":0.2855515564,"remaining_time":5.663439202},
{"learn":[6.431317261],"iteration":48,"passed_time":0.2885709397,"remaining_time":5.60063191},
{"learn":[6.377586395],"iteration":49,"passed_time":0.2906988799,"remaining_time":5.523278718},
{"learn":[6.327558015],"iteration":50,"passed_time":0.292944458,"remaining_time":5.451064522},
{"learn":[6.282040317],"iteration":51,"passed_time":0.2951025376,"remaining_time":5.379946263},
{"learn":[6.237655841],"iteration":52,"passed_time":0.297201054,"remaining_time":5.310366003},
{"learn":[6.192792003],"iteration":53,"passed_time":0.2988271799,"remaining_time":5.235009485},
{"learn":[6.150579347],"iteration":54,"passed_time":0.3003899729,"remaining_time":5.161245898},
{"learn":[6.115693845],"iteration":55,"passed_time":0.30199175,"remaining_time":5.090718071},
{"learn":[6.078780782],"iteration":56,"passed_time":0.3035636345,"remaining_time":5.022114164},
{"learn":[6.045146957],"iteration":57,"passed_time":0.3051415349,"remaining_time":4.955919411},
{"learn":[6.008080327],"iteration":58,"passed_time":0.3063758812,"remaining_time":4.886435665},
{"learn":[5.977575734],"iteration":59,"passed_time":0.3076692482,"remaining_time":4.820151556},
{"learn":[5.948036502],"iteration":60,"passed_time":0.3088684053,"remaining_time":4.754548076},
{"learn":[5.914888282],"iteration":61,"passed_time":0.3100623468,"remaining_time":4.690943246},
{"learn":[5.884957796],"iteration":62,"passed_time":0.3113106393,"remaining_time":4.63012808},
{"learn":[5.849539885],"iteration":63,"passed_time":0.3126026857,"remaining_time":4.571814278},
{"learn":[5.821387627],"iteration":64,"passed_time":0.3138095988,"remaining_time":4.514030383},
{"learn":[5.797012279],"iteration":65,"passed_time":0.3149882373,"remaining_time":4.457560813},
{"learn":[5.768685095],"iteration":66,"passed_time":0.3161058157,"remaining_time":4.401891433},
{"learn":[5.755484587],"iteration":67,"passed_time":0.3167147392,"remaining_time":4.340854954},
{"learn":[5.731887055],"iteration":68,"passed_time":0.3178109763,"remaining_time":4.288145202},
{"learn":[5.707148487],"iteration":69,"passed_time":0.3188721825,"remaining_time":4.236444711},
{"learn":[5.685365039],"iteration":70,"passed_time":0.3199402596,"remaining_time":4.18626058},
{"learn":[5.663541834],"iteration":71,"passed_time":0.3211309752,"remaining_time":4.139021458},
{"learn":[5.638108797],"iteration":72,"passed_time":0.3220999172,"remaining_time":4.090227715},
{"learn":[5.619204893],"iteration":73,"passed_time":0.3230619702,"remaining_time":4.04264033},
{"learn":[5.598472793],"iteration":74,"passed_time":0.324083552,"remaining_time":3.997030475},
{"learn":[5.577007075],"iteration":75,"passed_time":0.3251274824,"remaining_time":3.952865707},
{"learn":[5.562637084],"iteration":76,"passed_time":0.3261182476,"remaining_time":3.909183669},
{"learn":[5.54729991],"iteration":77,"passed_time":0.327105095,"remaining_time":3.866549969},
{"learn":[5.530737623],"iteration":78,"passed_time":0.3280837764,"remaining_time":3.824875419},
{"learn":[5.513704873],"iteration":79,"passed_time":0.3290677404,"remaining_time":3.784279015},
{"learn":[5.501575529],"iteration":80,"passed_time":0.3300687944,"remaining_time":3.744854594},
{"learn":[5.484080734],"iteration":81,"passed_time":0.3310414888,"remaining_time":3.706049839},
{"learn":[5.472178894],"iteration":82,"passed_time":0.3319997667,"remaining_time":3.667997422},
{"learn":[5.458923342],"iteration":83,"passed_time":0.3329494001,"remaining_time":3.630733935},
{"learn":[5.451382371],"iteration":84,"passed_time":0.3336561048,"remaining_time":3.591709834},
{"learn":[5.441410748],"iteration":85,"passed_time":0.3346763584,"remaining_time":3.556909204},
{"learn":[5.434047468],"iteration":86,"passed_time":0.3354071442,"remaining_time":3.519847386},
{"learn":[5.422107497],"iteration":87,"passed_time":0.3364003932,"remaining_time":3.486331348},
{"learn":[5.40731265],"iteration":88,"passed_time":0.3373905767,"remaining_time":3.453514779},
{"learn":[5.396360181],"iteration":89,"passed_time":0.3383892955,"remaining_time":3.421491765},
{"learn":[5.383793239],"iteration":90,"passed_time":0.3393676452,"remaining_time":3.389947137},
{"learn":[5.369605034],"iteration":91,"passed_time":0.3403195561,"remaining_time":3.358806054},
{"learn":[5.357467333],"iteration":92,"passed_time":0.3413012555,"remaining_time":3.328604718},
{"learn":[5.341109968],"iteration":93,"passed_time":0.3423308566,"remaining_time":3.299486767},
{"learn":[5.330529276],"iteration":94,"passed_time":0.3432941622,"remaining_time":3.270328598},
{"learn":[5.319862075],"iteration":95,"passed_time":0.3442619867,"remaining_time":3.241800375},
{"learn":[5.313052243],"iteration":96,"passed_time":0.3452029822,"remaining_time":3.213590649},
{"learn":[5.299677207],"iteration":97,"passed_time":0.3461765934,"remaining_time":3.186237625},
{"learn":[5.287546698],"iteration":98,"passed_time":0.3471393084,"remaining_time":3.159318352},
{"learn":[5.279803754],"iteration":99,"passed_time":0.3480886558,"remaining_time":3.132797902},
{"learn":[5.272254612],"iteration":100,"passed_time":0.3489999439,"remaining_time":3.106445045},
{"learn":[5.268813888],"iteration":101,"passed_time":0.3494924568,"remaining_time":3.076904178},
{"learn":[5.258113767],"iteration":102,"passed_time":0.3503775345,"remaining_time":3.051346102},
{"learn":[5.251018576],"iteration":103,"passed_time":0.3512558279,"remaining_time":3.026204056},
{"learn":[5.24171237],"iteration":104,"passed_time":0.3521385433,"remaining_time":3.001561869},
{"learn":[5.233984943],"iteration":105,"passed_time":0.3530597106,"remaining_time":2.977692276},
{"learn":[5.226240449],"iteration":106,"passed_time":0.3539351038,"remaining_time":2.953869605},
{"learn":[5.220541644],"iteration":107,"passed_time":0.3548613694,"remaining_time":2.930892051},
{"learn":[5.211712096],"iteration":108,"passed_time":0.3558860942,"remaining_time":2.909123944},
{"learn":[5.203388597],"iteration":109,"passed_time":0.3568609515,"remaining_time":2.887329517},
{"learn":[5.196026544],"iteration":110,"passed_time":0.3577912512,"remaining_time":2.865553354},
{"learn":[5.188716772],"iteration":111,"passed_time":0.3587471185,"remaining_time":2.844352154},
{"learn":[5.182163132],"iteration":112,"passed_time":0.3596835936,"remaining_time":2.823357057},
{"learn":[5.17764747],"iteration":113,"passed_time":0.3606224519,"remaining_time":2.802732389},
{"learn":[5.170548056],"iteration":114,"passed_time":0.3615495325,"remaining_time":2.782359446},
{"learn":[5.165901827],"iteration":115,"passed_time":0.3623447946,"remaining_time":2.761317228},
{"learn":[5.160333668],"iteration":116,"passed_time":0.3633166813,"remaining_time":2.741954099},
{"learn":[5.148953243],"iteration":117,"passed_time":0.3642826346,"remaining_time":2.722858336},
{"learn":[5.144729126],"iteration":118,"passed_time":0.3650225183,"remaining_time":2.702393602},
{"learn":[5.139939946],"iteration":119,"passed_time":0.3660281617,"remaining_time":2.684206519},
{"learn":[5.132898872],"iteration":120,"passed_time":0.3669966617,"remaining_time":2.666033601},
{"learn":[5.129073077],"iteration":121,"passed_time":0.3679639325,"remaining_time":2.648133875},
{"learn":[5.127123916],"iteration":122,"passed_time":0.3684943124,"remaining_time":2.627394407},
{"learn":[5.121282057],"iteration":123,"passed_time":0.3694531135,"remaining_time":2.61000748},
{"learn":[5.114489821],"iteration":124,"passed_time":0.3704133259,"remaining_time":2.592893281},
{"learn":[5.107777291],"iteration":125,"passed_time":0.3714019651,"remaining_time":2.576232678},
{"learn":[5.103518754],"iteration":126,"passed_time":0.3723853898,"remaining_time":2.559783034},
{"learn":[5.101133351],"iteration":127,"passed_time":0.3730005383,"remaining_time":2.541066167},
{"learn":[5.096462705],"iteration":128,"passed_time":0.3740012902,"remaining_time":2.525233518},
{"learn":[5.08562082],"iteration":129,"passed_time":0.3749862584,"remaining_time":2.509523421},
{"learn":[5.080483682],"iteration":130,"passed_time":0.3759642294,"remaining_time":2.49399172},
{"learn":[5.07437499],"iteration":131,"passed_time":0.3768778077,"remaining_time":2.478257099},
{"learn":[5.070683732],"iteration":132,"passed_time":0.3777900991,"remaining_time":2.462736962},
{"learn":[5.06432037],"iteration":133,"passed_time":0.3787366233,"remaining_time":2.447656088},
{"learn":[5.057436484],"iteration":134,"passed_time":0.3797509471,"remaining_time":2.433219032},
{"learn":[5.053254656],"iteration":135,"passed_time":0.3807222119,"remaining_time":2.418705817},
{"learn":[5.04801663],"iteration":136,"passed_time":0.3817107293,"remaining_time":2.404498974},
{"learn":[5.045680836],"iteration":137,"passed_time":0.3824772256,"remaining_time":2.389096873},
{"learn":[5.041857933],"iteration":138,"passed_time":0.3834604981,"remaining_time":2.375248121},
{"learn":[5.035264888],"iteration":139,"passed_time":0.3844082547,"remaining_time":2.361364993},
{"learn":[5.028771948],"iteration":140,"passed_time":0.3853951021,"remaining_time":2.347903494},
{"learn":[5.024912247],"iteration":141,"passed_time":0.3863948803,"remaining_time":2.334695826},
{"learn":[5.02239068],"iteration":142,"passed_time":0.3873502724,"remaining_time":2.321392891},
{"learn":[5.017110572],"iteration":143,"passed_time":0.3883387273,"remaining_time":2.30845799},
{"learn":[5.010707886],"iteration":144,"passed_time":0.3893612972,"remaining_time":2.295889028},
{"learn":[5.004389868],"iteration":145,"passed_time":0.390409492,"remaining_time":2.283628124},
{"learn":[4.997628683],"iteration":146,"passed_time":0.3913462852,"remaining_time":2.270873342},
{"learn":[4.991497851],"iteration":147,"passed_time":0.3923401934,"remaining_time":2.258607059},
{"learn":[4.988345253],"iteration":148,"passed_time":0.3933307831,"remaining_time":2.24647313},
{"learn":[4.98460423],"iteration":149,"passed_time":0.394324959,"remaining_time":2.234508101},
{"learn":[4.982441783],"iteration":150,"passed_time":0.3953026163,"remaining_time":2.222595505},
{"learn":[4.977461771],"iteration":151,"passed_time":0.3962610784,"remaining_time":2.210719701},
{"learn":[4.973601586],"iteration":152,"passed_time":0.3971979397,"remaining_time":2.198867026},
{"learn":[4.968328804],"iteration":153,"passed_time":0.3981673108,"remaining_time":2.187334708},
{"learn":[4.9640736],"iteration":154,"passed_time":0.3991146051,"remaining_time":2.175818331},
{"learn":[4.960865882],"iteration":155,"passed_time":0.4000327858,"remaining_time":2.164279943},
{"learn":[4.957014156],"iteration":156,"passed_time":0.4009643949,"remaining_time":2.152948948},
{"learn":[4.952244852],"iteration":157,"passed_time":0.401944857,"remaining_time":2.142009934},
{"learn":[4.949695675],"iteration":158,"passed_time":0.4029412871,"remaining_time":2.131280644},
{"learn":[4.946584698],"iteration":159,"passed_time":0.4039015499,"remaining_time":2.120483137},
{"learn":[4.940192834],"iteration":160,"passed_time":0.4048489139,"remaining_time":2.109740613},
{"learn":[4.936727994],"iteration":161,"passed_time":0.4057905425,"remaining_time":2.099089349},
{"learn":[4.932342063],"iteration":162,"passed_time":0.4067854652,"remaining_time":2.088830886},
{"learn":[4.925830838],"iteration":163,"passed_time":0.4077627755,"remaining_time":2.078595612},
{"learn":[4.922571773],"iteration":164,"passed_time":0.4087450126,"remaining_time":2.068497488},
{"learn":[4.918395814],"iteration":165,"passed_time":0.4097210423,"remaining_time":2.058478008},
{"learn":[4.911142452],"iteration":166,"passed_time":0.4106786951,"remaining_time":2.048475168},
{"learn":[4.908276131],"iteration":167,"passed_time":0.4116079402,"remaining_time":2.038439323},
{"learn":[4.904584645],"iteration":168,"passed_time":0.4126047045,"remaining_time":2.028843251},
{"learn":[4.89795517],"iteration":169,"passed_time":0.4135382713,"remaining_time":2.019039795},
{"learn":[4.895556491],"iteration":170,"passed_time":0.4145994094,"remaining_time":2.00995854},
{"learn":[4.890591233],"iteration":171,"passed_time":0.4155819478,"remaining_time":2.000592167},
{"learn":[4.884629277],"iteration":172,"passed_time":0.4165887612,"remaining_time":1.99143876},
{"learn":[4.880550786],"iteration":173,"passed_time":0.4175757072,"remaining_time":1.982284679},
{"learn":[4.876384842],"iteration":174,"passed_time":0.4184992618,"remaining_time":1.972925091},
{"learn":[4.872638238],"iteration":175,"passed_time":0.4195139478,"remaining_time":1.964088028},
{"learn":[4.869137118],"iteration":176,"passed_time":0.4204493089,"remaining_time":1.954970516},
{"learn":[4.863587157],"iteration":177,"passed_time":0.4214102401,"remaining_time":1.946063019},
{"learn":[4.858028614],"iteration":178,"passed_time":0.4224147215,"remaining_time":1.937444058},
{"learn":[4.853838176],"iteration":179,"passed_time":0.4233311151,"remaining_time":1.928508413},
{"learn":[4.853462329],"iteration":180,"passed_time":0.4238982874,"remaining_time":1.918081201},
{"learn":[4.851573196],"iteration":181,"passed_time":0.4248804123,"remaining_time":1.909627347},
{"learn":[4.848442087],"iteration":182,"passed_time":0.4258973638,"remaining_time":1.901410635},
{"learn":[4.845547104],"iteration":183,"passed_time":0.4268883787,"remaining_time":1.893157158},
{"learn":[4.839868817],"iteration":184,"passed_time":0.4279064413,"remaining_time":1.885101349},
{"learn":[4.836336958],"iteration":185,"passed_time":0.4289206713,"remaining_time":1.877104443},
{"learn":[4.831124789],"iteration":186,"passed_time":0.4299709573,"remaining_time":1.869338975},
{"learn":[4.827407333],"iteration":187,"passed_time":0.4310227767,"remaining_time":1.861651567},
{"learn":[4.824088918],"iteration":188,"passed_time":0.4319250638,"remaining_time":1.853392734},
{"learn":[4.820934539],"iteration":189,"passed_time":0.4328442029,"remaining_time":1.845283181},
{"learn":[4.816975227],"iteration":190,"passed_time":0.4339413151,"remaining_time":1.838002743},
{"learn":[4.812340486],"iteration":191,"passed_time":0.4348793865,"remaining_time":1.830117418},
{"learn":[4.806402747],"iteration":192,"passed_time":0.435906081,"remaining_time":1.82267465},
{"learn":[4.801521788],"iteration":193,"passed_time":0.436968607,"remaining_time":1.815446893},
{"learn":[4.797601172],"iteration":194,"passed_time":0.4380335436,"remaining_time":1.808292321},
{"learn":[4.792694629],"iteration":195,"passed_time":0.4389917918,"remaining_time":1.800762248},
{"learn":[4.789794613],"iteration":196,"passed_time":0.4400643233,"remaining_time":1.793764729},
{"learn":[4.785367055],"iteration":197,"passed_time":0.4411181802,"remaining_time":1.786751417},
{"learn":[4.780376856],"iteration":198,"passed_time":0.4421619582,"remaining_time":1.77975743},
{"learn":[4.776691261],"iteration":199,"passed_time":0.4432002189,"remaining_time":1.772800876},
{"learn":[4.773470753],"iteration":200,"passed_time":0.4442246247,"remaining_time":1.765848135},
{"learn":[4.77207327],"iteration":201,"passed_time":0.4459645002,"remaining_time":1.76178055},
{"learn":[4.767347177],"iteration":202,"passed_time":0.4472313063,"remaining_time":1.755878577},
{"learn":[4.763983068],"iteration":203,"passed_time":0.4482486933,"remaining_time":1.749048823},
{"learn":[4.761588849],"iteration":204,"passed_time":0.4493038472,"remaining_time":1.742422237},
{"learn":[4.758558086],"iteration":205,"passed_time":0.4502329593,"remaining_time":1.73536393},
{"learn":[4.753678804],"iteration":206,"passed_time":0.4513201318,"remaining_time":1.72897036},
{"learn":[4.746510889],"iteration":207,"passed_time":0.4523591045,"remaining_time":1.722444282},
{"learn":[4.744840601],"iteration":208,"passed_time":0.4533327637,"remaining_time":1.715723522},
{"learn":[4.741702222],"iteration":209,"passed_time":0.4543784502,"remaining_time":1.709328456},
{"learn":[4.739352853],"iteration":210,"passed_time":0.4554013403,"remaining_time":1.702898851},
{"learn":[4.735539287],"iteration":211,"passed_time":0.4563258245,"remaining_time":1.69615448},
{"learn":[4.730726751],"iteration":212,"passed_time":0.4572315655,"remaining_time":1.689395502},
{"learn":[4.726416092],"iteration":213,"passed_time":0.4582670013,"remaining_time":1.683167584},
{"learn":[4.721293082],"iteration":214,"passed_time":0.4592562423,"remaining_time":1.676819303},
{"learn":[4.718443695],"iteration":215,"passed_time":0.4602918833,"remaining_time":1.670689058},
{"learn":[4.711627962],"iteration":216,"passed_time":0.4612509762,"remaining_time":1.664329559},
{"learn":[4.709790764],"iteration":217,"passed_time":0.4621843403,"remaining_time":1.657927312},
{"learn":[4.706913073],"iteration":218,"passed_time":0.4631384967,"remaining_time":1.651649159},
{"learn":[4.703846389],"iteration":219,"passed_time":0.4641112704,"remaining_time":1.645485413},
{"learn":[4.701001135],"iteration":220,"passed_time":0.4650095563,"remaining_time":1.639106083},
{"learn":[4.700380864],"iteration":221,"passed_time":0.4659550908,"remaining_time":1.632941715},
{"learn":[4.695837486],"iteration":222,"passed_time":0.4669647723,"remaining_time":1.62704766},
{"learn":[4.691242996],"iteration":223,"passed_time":0.4680113143,"remaining_time":1.62132491},
{"learn":[4.690284609],"iteration":224,"passed_time":0.4689171915,"remaining_time":1.615159215},
{"learn":[4.68827119],"iteration":225,"passed_time":0.4698813097,"remaining_time":1.60923953},
{"learn":[4.686922425],"iteration":226,"passed_time":0.4709371684,"remaining_time":1.603675908},
{"learn":[4.686085874],"iteration":227,"passed_time":0.4718905443,"remaining_time":1.597804825},
{"learn":[4.683230741],"iteration":228,"passed_time":0.4729048929,"remaining_time":1.592181976},
{"learn":[4.6773487],"iteration":229,"passed_time":0.4739350125,"remaining_time":1.586651998},
{"learn":[4.671462906],"iteration":230,"passed_time":0.4749468577,"remaining_time":1.581100145},
{"learn":[4.664799601],"iteration":231,"passed_time":0.4759400302,"remaining_time":1.575525617},
{"learn":[4.660979386],"iteration":232,"passed_time":0.4769625865,"remaining_time":1.570087141},
{"learn":[4.656281279],"iteration":233,"passed_time":0.4779715668,"remaining_time":1.564641967},
{"learn":[4.651997094],"iteration":234,"passed_time":0.4788482719,"remaining_time":1.558803949},
{"learn":[4.650151977],"iteration":235,"passed_time":0.4797124116,"remaining_time":1.552967298},
{"learn":[4.648478046],"iteration":236,"passed_time":0.4805617171,"remaining_time":1.547124853},
{"learn":[4.646364602],"iteration":237,"passed_time":0.4815255372,"remaining_time":1.541691006},
{"learn":[4.642635873],"iteration":238,"passed_time":0.4824698424,"remaining_time":1.536232427},
{"learn":[4.640860821],"iteration":239,"passed_time":0.4834000884,"remaining_time":1.530766946},
{"learn":[4.639446822],"iteration":240,"passed_time":0.4842712736,"remaining_time":1.525153098},
{"learn":[4.637120072],"iteration":241,"passed_time":0.4851234633,"remaining_time":1.519518947},
{"learn":[4.633769267],"iteration":242,"passed_time":0.4860023954,"remaining_time":1.514007462},
{"learn":[4.630491517],"iteration":243,"passed_time":0.4869092455,"remaining_time":1.508620449},
{"learn":[4.627813333],"iteration":244,"passed_time":0.487857285,"remaining_time":1.50339694},
{"learn":[4.622496304],"iteration":245,"passed_time":0.4888094276,"remaining_time":1.498220766},
{"learn":[4.618979301],"iteration":246,"passed_time":0.4897752727,"remaining_time":1.493120568},
{"learn":[4.616563458],"iteration":247,"passed_time":0.4907937604,"remaining_time":1.488213338},
{"learn":[4.614759385],"iteration":248,"passed_time":0.4918251578,"remaining_time":1.483376279},
{"learn":[4.61251363],"iteration":249,"passed_time":0.4928942699,"remaining_time":1.47868281},
{"learn":[4.608796693],"iteration":250,"passed_time":0.493863024,"remaining_time":1.473718745},
{"learn":[4.60847774],"iteration":251,"passed_time":0.4947836568,"remaining_time":1.468643553},
{"learn":[4.605195659],"iteration":252,"passed_time":0.495767616,"remaining_time":1.463788179},
{"learn":[4.60103766],"iteration":253,"passed_time":0.4967048083,"remaining_time":1.458825933},
{"learn":[4.599325598],"iteration":254,"passed_time":0.4976533791,"remaining_time":1.4539285},
{"learn":[4.597012808],"iteration":255,"passed_time":0.4985819695,"remaining_time":1.449003849},
{"learn":[4.594161533],"iteration":256,"passed_time":0.4995892814,"remaining_time":1.444337884},
{"learn":[4.592197259],"iteration":257,"passed_time":0.5005940838,"remaining_time":1.439693063},
{"learn":[4.58952828],"iteration":258,"passed_time":0.5015663166,"remaining_time":1.434983168},
{"learn":[4.585816572],"iteration":259,"passed_time":0.5025245664,"remaining_time":1.430262227},
{"learn":[4.582934052],"iteration":260,"passed_time":0.5035136247,"remaining_time":1.425657351},
{"learn":[4.582234842],"iteration":261,"passed_time":0.5044478583,"remaining_time":1.420925647},
{"learn":[4.57571562],"iteration":262,"passed_time":0.5054629971,"remaining_time":1.41644954},
{"learn":[4.571197349],"iteration":263,"passed_time":0.506449072,"remaining_time":1.411918625},
{"learn":[4.56723703],"iteration":264,"passed_time":0.507365718,"remaining_time":1.407221897},
{"learn":[4.560335567],"iteration":265,"passed_time":0.5084482478,"remaining_time":1.40301133},
{"learn":[4.554709345],"iteration":266,"passed_time":0.509373954,"remaining_time":1.398393664},
{"learn":[4.552806306],"iteration":267,"passed_time":0.5103353964,"remaining_time":1.393901157},
{"learn":[4.550766241],"iteration":268,"passed_time":0.5112427811,"remaining_time":1.389288004},
{"learn":[4.549216045],"iteration":269,"passed_time":0.5121745489,"remaining_time":1.384768225},
{"learn":[4.547687452],"iteration":270,"passed_time":0.5131166647,"remaining_time":1.380302762},
{"learn":[4.545642435],"iteration":271,"passed_time":0.514043811,"remaining_time":1.375823141},
{"learn":[4.543930359],"iteration":272,"passed_time":0.5149873341,"remaining_time":1.371413157},
{"learn":[4.541029943],"iteration":273,"passed_time":0.5159538564,"remaining_time":1.367089415},
{"learn":[4.537781449],"iteration":274,"passed_time":0.5169093182,"remaining_time":1.36276093},
{"learn":[4.53066128],"iteration":275,"passed_time":0.5178634778,"remaining_time":1.358453471},
{"learn":[4.526763956],"iteration":276,"passed_time":0.5188219199,"remaining_time":1.354181401},
{"learn":[4.522036004],"iteration":277,"passed_time":0.5198168266,"remaining_time":1.350027873},
{"learn":[4.515307629],"iteration":278,"passed_time":0.5208180256,"remaining_time":1.345913249},
{"learn":[4.51109143],"iteration":279,"passed_time":0.5218143235,"remaining_time":1.34180826},
{"learn":[4.508233494],"iteration":280,"passed_time":0.5227670839,"remaining_time":1.337613998},
{"learn":[4.502555629],"iteration":281,"passed_time":0.5237302196,"remaining_time":1.333469141},
{"learn":[4.500081355],"iteration":282,"passed_time":0.5246962763,"remaining_time":1.32935417},
{"learn":[4.495281743],"iteration":283,"passed_time":0.5256647155,"remaining_time":1.325267381},
{"learn":[4.492138869],"iteration":284,"passed_time":0.526658005,"remaining_time":1.32126482},
{"learn":[4.491708261],"iteration":285,"passed_time":0.5275608042,"remaining_time":1.317057392},
{"learn":[4.489398865],"iteration":286,"passed_time":0.5285160986,"remaining_time":1.313003409},
{"learn":[4.485796373],"iteration":287,"passed_time":0.5296096916,"remaining_time":1.309312849},
{"learn":[4.479542205],"iteration":288,"passed_time":0.5305604406,"remaining_time":1.305288835},
{"learn":[4.475986993],"iteration":289,"passed_time":0.5315331478,"remaining_time":1.301339776},
{"learn":[4.468661855],"iteration":290,"passed_time":0.5324861879,"remaining_time":1.297363255},
{"learn":[4.463785664],"iteration":291,"passed_time":0.5334634814,"remaining_time":1.293466249},
{"learn":[4.460445831],"iteration":292,"passed_time":0.534391183,"remaining_time":1.28946951},
{"learn":[4.45692492],"iteration":293,"passed_time":0.5353893706,"remaining_time":1.28566291},
{"learn":[4.454031688],"iteration":294,"passed_time":0.5363482262,"remaining_time":1.281781354},
{"learn":[4.451672391],"iteration":295,"passed_time":0.5373044597,"remaining_time":1.27791331},
{"learn":[4.45031553],"iteration":296,"passed_time":0.5383043637,"remaining_time":1.274168241},
{"learn":[4.446782666],"iteration":297,"passed_time":0.5393085078,"remaining_time":1.270451585},
{"learn":[4.444369689],"iteration":298,"passed_time":0.5403162844,"remaining_time":1.26676159},
{"learn":[4.44411683],"iteration":299,"passed_time":0.5412071825,"remaining_time":1.262816759},
{"learn":[4.440876943],"iteration":300,"passed_time":0.5422113563,"remaining_time":1.259155276},
{"learn":[4.439336453],"iteration":301,"passed_time":0.5431749808,"remaining_time":1.255417671},
{"learn":[4.436666901],"iteration":302,"passed_time":0.5441397281,"remaining_time":1.251700959},
{"learn":[4.433043336],"iteration":303,"passed_time":0.5451014558,"remaining_time":1.247995438},
{"learn":[4.431419305],"iteration":304,"passed_time":0.5461364124,"remaining_time":1.244474776},
{"learn":[4.428859646],"iteration":305,"passed_time":0.5470990729,"remaining_time":1.240806394},
{"learn":[4.424552441],"iteration":306,"passed_time":0.5481221244,"remaining_time":1.237291962},
{"learn":[4.422706391],"iteration":307,"passed_time":0.5491010166,"remaining_time":1.233694492},
{"learn":[4.421427994],"iteration":308,"passed_time":0.5500451166,"remaining_time":1.230036167},
{"learn":[4.418733158],"iteration":309,"passed_time":0.551019909,"remaining_time":1.226463668},
{"learn":[4.415656941],"iteration":310,"passed_time":0.5520108145,"remaining_time":1.222943573},
{"learn":[4.410747417],"iteration":311,"passed_time":0.5529884854,"remaining_time":1.219410506},
{"learn":[4.408126521],"iteration":312,"passed_time":0.5539560455,"remaining_time":1.215871576},
{"learn":[4.407843853],"iteration":313,"passed_time":0.5548996487,"remaining_time":1.212296685},
{"learn":[4.405219398],"iteration":314,"passed_time":0.5558816309,"remaining_time":1.208821959},
{"learn":[4.402708465],"iteration":315,"passed_time":0.5568609374,"remaining_time":1.205357219},
{"learn":[4.40104971],"iteration":316,"passed_time":0.5578453326,"remaining_time":1.201919124},
{"learn":[4.400830038],"iteration":317,"passed_time":0.5587622046,"remaining_time":1.198351646},
{"learn":[4.39784288],"iteration":318,"passed_time":0.559754575,"remaining_time":1.194961961},
{"learn":[4.393741845],"iteration":319,"passed_time":0.5607443826,"remaining_time":1.191581813},
{"learn":[4.393425936],"iteration":320,"passed_time":0.561682022,"remaining_time":1.188106209},
{"learn":[4.390505974],"iteration":321,"passed_time":0.5626742529,"remaining_time":1.184761315},
{"learn":[4.390305136],"iteration":322,"passed_time":0.5636166765,"remaining_time":1.181326594},
{"learn":[4.38568203],"iteration":323,"passed_time":0.5646246968,"remaining_time":1.17804412},
{"learn":[4.383057135],"iteration":324,"passed_time":0.5656078218,"remaining_time":1.174723938},
{"learn":[4.380662684],"iteration":325,"passed_time":0.5665641291,"remaining_time":1.171362647},
{"learn":[4.37805727],"iteration":326,"passed_time":0.5674873006,"remaining_time":1.167947869},
{"learn":[4.373708319],"iteration":327,"passed_time":0.5684901216,"remaining_time":1.164711469},
{"learn":[4.36887921],"iteration":328,"passed_time":0.5694654942,"remaining_time":1.161432664},
{"learn":[4.367895929],"iteration":329,"passed_time":0.570378014,"remaining_time":1.15804021},
{"learn":[4.362140573],"iteration":330,"passed_time":0.5713858683,"remaining_time":1.154855426},
{"learn":[4.361931924],"iteration":331,"passed_time":0.5722956611,"remaining_time":1.151486451},
{"learn":[4.359656377],"iteration":332,"passed_time":0.5732841152,"remaining_time":1.148289804},
{"learn":[4.354281355],"iteration":333,"passed_time":0.5742268737,"remaining_time":1.145015263},
{"learn":[4.348589447],"iteration":334,"passed_time":0.5752083175,"remaining_time":1.141831436},
{"learn":[4.346355698],"iteration":335,"passed_time":0.5761492152,"remaining_time":1.138580592},
{"learn":[4.343894047],"iteration":336,"passed_time":0.5771388433,"remaining_time":1.135439327},
{"learn":[4.341561356],"iteration":337,"passed_time":0.5781197133,"remaining_time":1.13229364},
{"learn":[4.338869061],"iteration":338,"passed_time":0.5791027646,"remaining_time":1.129164978},
{"learn":[4.333720063],"iteration":339,"passed_time":0.5801523578,"remaining_time":1.126178106},
{"learn":[4.330892223],"iteration":340,"passed_time":0.58124949,"remaining_time":1.123294469},
{"learn":[4.328311474],"iteration":341,"passed_time":0.5822322044,"remaining_time":1.120201142},
{"learn":[4.324580133],"iteration":342,"passed_time":0.583235501,"remaining_time":1.117159546},
{"learn":[4.323354432],"iteration":343,"passed_time":0.5842341424,"remaining_time":1.114120923},
{"learn":[4.323159553],"iteration":344,"passed_time":0.5853624531,"remaining_time":1.11134031},
{"learn":[4.318639682],"iteration":345,"passed_time":0.5863758862,"remaining_time":1.108352109},
{"learn":[4.312712208],"iteration":346,"passed_time":0.5874013386,"remaining_time":1.105397908},
{"learn":[4.311461062],"iteration":347,"passed_time":0.588299437,"remaining_time":1.102216187},
{"learn":[4.311178356],"iteration":348,"passed_time":0.5891772287,"remaining_time":1.099009673},
{"learn":[4.311102505],"iteration":349,"passed_time":0.590049338,"remaining_time":1.095805913},
{"learn":[4.310232308],"iteration":350,"passed_time":0.5910051756,"remaining_time":1.092770254},
{"learn":[4.305128197],"iteration":351,"passed_time":0.5919637684,"remaining_time":1.089751483},
{"learn":[4.304595496],"iteration":352,"passed_time":0.5929191276,"remaining_time":1.086738458},
{"learn":[4.3004992],"iteration":353,"passed_time":0.5939244673,"remaining_time":1.083828265},
{"learn":[4.297581524],"iteration":354,"passed_time":0.5949054247,"remaining_time":1.080884504},
{"learn":[4.297355825],"iteration":355,"passed_time":0.5958573492,"remaining_time":1.07789925},
{"learn":[4.295758715],"iteration":356,"passed_time":0.5967910035,"remaining_time":1.07489248},
{"learn":[4.292500657],"iteration":357,"passed_time":0.5978128417,"remaining_time":1.072055431},
{"learn":[4.290797586],"iteration":358,"passed_time":0.5988363909,"remaining_time":1.06923155},
{"learn":[4.286410608],"iteration":359,"passed_time":0.5998568764,"remaining_time":1.066412225},
{"learn":[4.280278245],"iteration":360,"passed_time":0.6009000126,"remaining_time":1.063642959},
{"learn":[4.279941283],"iteration":361,"passed_time":0.6017795713,"remaining_time":1.060594935},
{"learn":[4.274426275],"iteration":362,"passed_time":0.6028020411,"remaining_time":1.057809642},
{"learn":[4.273567658],"iteration":363,"passed_time":0.6037797985,"remaining_time":1.054955912},
{"learn":[4.269488271],"iteration":364,"passed_time":0.6047702624,"remaining_time":1.052134566},
{"learn":[4.266838205],"iteration":365,"passed_time":0.6057094052,"remaining_time":1.049234325},
{"learn":[4.263456509],"iteration":366,"passed_time":0.6067260033,"remaining_time":1.046478365},
{"learn":[4.260360204],"iteration":367,"passed_time":0.6076647254,"remaining_time":1.043598115},
{"learn":[4.255120549],"iteration":368,"passed_time":0.6086684199,"remaining_time":1.040839493},
{"learn":[4.252582211],"iteration":369,"passed_time":0.6096362748,"remaining_time":1.038029333},
{"learn":[4.247857931],"iteration":370,"passed_time":0.6106253236,"remaining_time":1.035265036},
{"learn":[4.245288911],"iteration":371,"passed_time":0.6115738592,"remaining_time":1.032441891},
{"learn":[4.24048515],"iteration":372,"passed_time":0.6125668121,"remaining_time":1.029703462},
{"learn":[4.2378365],"iteration":373,"passed_time":0.6135335348,"remaining_time":1.026930462},
{"learn":[4.236751063],"iteration":374,"passed_time":0.6144856012,"remaining_time":1.024142669},
{"learn":[4.233240093],"iteration":375,"passed_time":0.6154878677,"remaining_time":1.021447951},
{"learn":[4.230358421],"iteration":376,"passed_time":0.616463007,"remaining_time":1.018717383},
{"learn":[4.225853583],"iteration":377,"passed_time":0.6174330521,"remaining_time":1.015987721},
{"learn":[4.224702126],"iteration":378,"passed_time":0.618407278,"remaining_time":1.013274194},
{"learn":[4.224361982],"iteration":379,"passed_time":0.6193441024,"remaining_time":1.010508799},
{"learn":[4.223787954],"iteration":380,"passed_time":0.620282447,"remaining_time":1.007755472},
{"learn":[4.22144054],"iteration":381,"passed_time":0.6212795246,"remaining_time":1.005106665},
{"learn":[4.217739335],"iteration":382,"passed_time":0.6222570264,"remaining_time":1.002434949},
{"learn":[4.215611665],"iteration":383,"passed_time":0.6232367617,"remaining_time":0.9997756385},
{"learn":[4.210236863],"iteration":384,"passed_time":0.6242203194,"remaining_time":0.9971311596},
{"learn":[4.208454294],"iteration":385,"passed_time":0.6251936613,"remaining_time":0.9944790364},
{"learn":[4.207446501],"iteration":386,"passed_time":0.6261039196,"remaining_time":0.991735666},
{"learn":[4.204985442],"iteration":387,"passed_time":0.6270352707,"remaining_time":0.9890350147},
{"learn":[4.202796622],"iteration":388,"passed_time":0.628001777,"remaining_time":0.986398678},
{"learn":[4.199774004],"iteration":389,"passed_time":0.6290081024,"remaining_time":0.9838331858},
{"learn":[4.199458358],"iteration":390,"passed_time":0.6299758656,"remaining_time":0.9812156065},
{"learn":[4.19751254],"iteration":391,"passed_time":0.6309730562,"remaining_time":0.9786520871},
{"learn":[4.195201346],"iteration":392,"passed_time":0.6319601984,"remaining_time":0.976081019},
{"learn":[4.190593508],"iteration":393,"passed_time":0.6329360759,"remaining_time":0.973500665},
{"learn":[4.187212054],"iteration":394,"passed_time":0.6338821561,"remaining_time":0.9708827961},
{"learn":[4.184984466],"iteration":395,"passed_time":0.6348570367,"remaining_time":0.9683172983},
{"learn":[4.182832144],"iteration":396,"passed_time":0.6358014621,"remaining_time":0.9657135557},
{"learn":[4.179752812],"iteration":397,"passed_time":0.636786657,"remaining_time":0.9631798179},
{"learn":[4.17878934],"iteration":398,"passed_time":0.6377066952,"remaining_time":0.9605556988},
{"learn":[4.174548229],"iteration":399,"passed_time":0.6387188906,"remaining_time":0.9580783359},
{"learn":[4.168872556],"iteration":400,"passed_time":0.6396700955,"remaining_time":0.9555171751},
{"learn":[4.163926494],"iteration":401,"passed_time":0.6406486111,"remaining_time":0.9530046503},
{"learn":[4.159485076],"iteration":402,"passed_time":0.6416426219,"remaining_time":0.9505226929},
{"learn":[4.155926102],"iteration":403,"passed_time":0.6426660035,"remaining_time":0.948091431},
{"learn":[4.153540115],"iteration":404,"passed_time":0.6436590142,"remaining_time":0.9456225024},
{"learn":[4.150983044],"iteration":405,"passed_time":0.644753522,"remaining_time":0.9433093401},
{"learn":[4.146539132],"iteration":406,"passed_time":0.6457699871,"remaining_time":0.9408884579},
{"learn":[4.144869174],"iteration":407,"passed_time":0.6467282561,"remaining_time":0.9383900187},
{"learn":[4.142825962],"iteration":408,"passed_time":0.647693283,"remaining_time":0.935908876},
{"learn":[4.142467378],"iteration":409,"passed_time":0.6486093417,"remaining_time":0.9333646624},
{"learn":[4.141800768],"iteration":410,"passed_time":0.6495417714,"remaining_time":0.930851833},
{"learn":[4.140107084],"iteration":411,"passed_time":0.6505455067,"remaining_time":0.9284484417},
{"learn":[4.136243196],"iteration":412,"passed_time":0.6515432295,"remaining_time":0.9260432825},
{"learn":[4.133618439],"iteration":413,"passed_time":0.6524558871,"remaining_time":0.9235245165},
{"learn":[4.131053025],"iteration":414,"passed_time":0.6533943663,"remaining_time":0.9210498899},
{"learn":[4.128379975],"iteration":415,"passed_time":0.6544079673,"remaining_time":0.918688108},
{"learn":[4.127068571],"iteration":416,"passed_time":0.6553480822,"remaining_time":0.9162300525},
{"learn":[4.125969877],"iteration":417,"passed_time":0.6563237304,"remaining_time":0.9138287347},
{"learn":[4.123893633],"iteration":418,"passed_time":0.6572893287,"remaining_time":0.9114202864},
{"learn":[4.119643722],"iteration":419,"passed_time":0.6583508595,"remaining_time":0.9091511869},
{"learn":[4.11465686],"iteration":420,"passed_time":0.6593395339,"remaining_time":0.9067876251},
{"learn":[4.111565986],"iteration":421,"passed_time":0.6603114911,"remaining_time":0.9044076821},
{"learn":[4.106322452],"iteration":422,"passed_time":0.6612736211,"remaining_time":0.9020209914},
{"learn":[4.104222175],"iteration":423,"passed_time":0.6622385767,"remaining_time":0.8996448589},
{"learn":[4.103008002],"iteration":424,"passed_time":0.6631949184,"remaining_time":0.8972637132},
{"learn":[4.099176337],"iteration":425,"passed_time":0.6641619961,"remaining_time":0.8949037224},
{"learn":[4.096525716],"iteration":426,"passed_time":0.6651243913,"remaining_time":0.8925439724},
{"learn":[4.094967724],"iteration":427,"passed_time":0.6661166896,"remaining_time":0.890230716},
{"learn":[4.094683584],"iteration":428,"passed_time":0.6670571113,"remaining_time":0.8878545701},
{"learn":[4.091096563],"iteration":429,"passed_time":0.668033565,"remaining_time":0.8855328652},
{"learn":[4.089178677],"iteration":430,"passed_time":0.668943562,"remaining_time":0.8831296677},
{"learn":[4.085335077],"iteration":431,"passed_time":0.6699784365,"remaining_time":0.8808975739},
{"learn":[4.084852122],"iteration":432,"passed_time":0.6710086298,"remaining_time":0.8786648801},
{"learn":[4.080322952],"iteration":433,"passed_time":0.6719738178,"remaining_time":0.8763529514},
{"learn":[4.077449519],"iteration":434,"passed_time":0.6729744042,"remaining_time":0.8740931917},
{"learn":[4.076568374],"iteration":435,"passed_time":0.6738935609,"remaining_time":0.8717338724},
{"learn":[4.076071793],"iteration":436,"passed_time":0.6748466883,"remaining_time":0.8694249097},
{"learn":[4.075027644],"iteration":437,"passed_time":0.6758433605,"remaining_time":0.8671780105},
{"learn":[4.07020837],"iteration":438,"passed_time":0.6768160901,"remaining_time":0.8649062109},
{"learn":[4.06833694],"iteration":439,"passed_time":0.6777642723,"remaining_time":0.8626090739},
{"learn":[4.063936568],"iteration":440,"passed_time":0.6787871027,"remaining_time":0.8604126766},
{"learn":[4.061734926],"iteration":441,"passed_time":0.679754246,"remaining_time":0.858151288},
{"learn":[4.060815619],"iteration":442,"passed_time":0.6807008616,"remaining_time":0.855869932},
{"learn":[4.056407489],"iteration":443,"passed_time":0.6816862312,"remaining_time":0.8536431183},
{"learn":[4.05238936],"iteration":444,"passed_time":0.6826786713,"remaining_time":0.8514307024},
{"learn":[4.049685254],"iteration":445,"passed_time":0.6835983457,"remaining_time":0.8491333711},
{"learn":[4.045162016],"iteration":446,"passed_time":0.6845646484,"remaining_time":0.8468998894},
{"learn":[4.042955482],"iteration":447,"passed_time":0.6855303829,"remaining_time":0.8446713647},
{"learn":[4.041467663],"iteration":448,"passed_time":0.6865293566,"remaining_time":0.8424892549},
{"learn":[4.038920476],"iteration":449,"passed_time":0.6875277757,"remaining_time":0.8403117258},
{"learn":[4.036694383],"iteration":450,"passed_time":0.6885093172,"remaining_time":0.8381188805},
{"learn":[4.034999007],"iteration":451,"passed_time":0.6894572638,"remaining_time":0.8358906649},
{"learn":[4.031928018],"iteration":452,"passed_time":0.6904074766,"remaining_time":0.8336708382},
{"learn":[4.028718143],"iteration":453,"passed_time":0.6913721766,"remaining_time":0.8314740274},
{"learn":[4.027401978],"iteration":454,"passed_time":0.6922661439,"remaining_time":0.8291979087},
{"learn":[4.025930598],"iteration":455,"passed_time":0.6932187457,"remaining_time":0.8269978019},
{"learn":[4.021074523],"iteration":456,"passed_time":0.6942073416,"remaining_time":0.8248459223},
{"learn":[4.020268486],"iteration":457,"passed_time":0.6951227559,"remaining_time":0.822612519},
{"learn":[4.017986361],"iteration":458,"passed_time":0.6961186804,"remaining_time":0.8204797518},
{"learn":[4.014814804],"iteration":459,"passed_time":0.697062096,"remaining_time":0.8182902867},
{"learn":[4.009704796],"iteration":460,"passed_time":0.6980262904,"remaining_time":0.8161305217},
{"learn":[4.008440457],"iteration":461,"passed_time":0.6989868016,"remaining_time":0.8139716434},
{"learn":[4.004854849],"iteration":462,"passed_time":0.6999800984,"remaining_time":0.8118559672},
{"learn":[4.000898028],"iteration":463,"passed_time":0.7009796858,"remaining_time":0.8097523957},
{"learn":[3.996617985],"iteration":464,"passed_time":0.7019568198,"remaining_time":0.807627739},
{"learn":[3.995443319],"iteration":465,"passed_time":0.7029088406,"remaining_time":0.8054792293},
{"learn":[3.990771995],"iteration":466,"passed_time":0.7038780475,"remaining_time":0.8033554589},
{"learn":[3.989249359],"iteration":467,"passed_time":0.7049161446,"remaining_time":0.8013149336},
{"learn":[3.986599538],"iteration":468,"passed_time":0.7059259207,"remaining_time":0.7992466181},
{"learn":[3.985628919],"iteration":469,"passed_time":0.7068841593,"remaining_time":0.7971246902},
{"learn":[3.985086112],"iteration":470,"passed_time":0.7078804491,"remaining_time":0.7950504407},
{"learn":[3.98466839],"iteration":471,"passed_time":0.7088777543,"remaining_time":0.7929818947},
{"learn":[3.984233894],"iteration":472,"passed_time":0.709787773,"remaining_time":0.7908206266},
{"learn":[3.981855845],"iteration":473,"passed_time":0.7107411184,"remaining_time":0.7887127179},
{"learn":[3.978684264],"iteration":474,"passed_time":0.7116902166,"remaining_time":0.7866049762},
{"learn":[3.974361269],"iteration":475,"passed_time":0.7127141007,"remaining_time":0.7845844302},
{"learn":[3.972074049],"iteration":476,"passed_time":0.7136655076,"remaining_time":0.7824885964},
{"learn":[3.97191982],"iteration":477,"passed_time":0.7146230162,"remaining_time":0.7804042143},
{"learn":[3.969616848],"iteration":478,"passed_time":0.715549293,"remaining_time":0.7782905671},
{"learn":[3.968533527],"iteration":479,"passed_time":0.7164879806,"remaining_time":0.7761953123},
{"learn":[3.967568753],"iteration":480,"passed_time":0.7174440891,"remaining_time":0.7741236637},
{"learn":[3.966232553],"iteration":481,"passed_time":0.7184172002,"remaining_time":0.7720749164},
{"learn":[3.961522393],"iteration":482,"passed_time":0.7193889346,"remaining_time":0.7700291495},
{"learn":[3.955829553],"iteration":483,"passed_time":0.7203401901,"remaining_time":0.7679659878},
{"learn":[3.954248095],"iteration":484,"passed_time":0.7212507946,"remaining_time":0.7658642458},
{"learn":[3.951922606],"iteration":485,"passed_time":0.722219394,"remaining_time":0.7638287418},
{"learn":[3.94978202],"iteration":486,"passed_time":0.7231955463,"remaining_time":0.7618055755},
{"learn":[3.949518999],"iteration":487,"passed_time":0.724104363,"remaining_time":0.759716053},
{"learn":[3.945431216],"iteration":488,"passed_time":0.7250563132,"remaining_time":0.7576764336},
{"learn":[3.943249086],"iteration":489,"passed_time":0.7260241425,"remaining_time":0.755657781},
{"learn":[3.941981548],"iteration":490,"passed_time":0.7269931074,"remaining_time":0.7536445859},
{"learn":[3.936600517],"iteration":491,"passed_time":0.7279658899,"remaining_time":0.7516395774},
{"learn":[3.934476885],"iteration":492,"passed_time":0.7289372693,"remaining_time":0.7496373135},
{"learn":[3.93045798],"iteration":493,"passed_time":0.7299300219,"remaining_time":0.7476611156},
{"learn":[3.925977375],"iteration":494,"passed_time":0.7309245857,"remaining_time":0.7456907389},
{"learn":[3.92457993],"iteration":495,"passed_time":0.7318607586,"remaining_time":0.7436649644},
{"learn":[3.919849146],"iteration":496,"passed_time":0.7328183376,"remaining_time":0.7416652391},
{"learn":[3.919681964],"iteration":497,"passed_time":0.733759475,"remaining_time":0.7396531254},
{"learn":[3.917633027],"iteration":498,"passed_time":0.7347293759,"remaining_time":0.737674183},
{"learn":[3.916616419],"iteration":499,"passed_time":0.7356945102,"remaining_time":0.7356945102},
{"learn":[3.912896166],"iteration":500,"passed_time":0.7366756422,"remaining_time":0.7337348213},
{"learn":[3.912769674],"iteration":501,"passed_time":0.7375642852,"remaining_time":0.731687279},
{"learn":[3.909373788],"iteration":502,"passed_time":0.738503452,"remaining_time":0.7296942657},
{"learn":[3.906706036],"iteration":503,"passed_time":0.7395001923,"remaining_time":0.727762094},
{"learn":[3.903895664],"iteration":504,"passed_time":0.7404836042,"remaining_time":0.7258205625},
{"learn":[3.902982967],"iteration":505,"passed_time":0.741474593,"remaining_time":0.7238902153},
{"learn":[3.900905528],"iteration":506,"passed_time":0.7424450524,"remaining_time":0.7219436111},
{"learn":[3.897463465],"iteration":507,"passed_time":0.7434263928,"remaining_time":0.7200113883},
{"learn":[3.895918033],"iteration":508,"passed_time":0.7443404415,"remaining_time":0.7180179898},
{"learn":[3.893921936],"iteration":509,"passed_time":0.745321237,"remaining_time":0.7160929532},
{"learn":[3.890237934],"iteration":510,"passed_time":0.7462943465,"remaining_time":0.7141642572},
{"learn":[3.887311613],"iteration":511,"passed_time":0.7472724197,"remaining_time":0.712244025},
{"learn":[3.884869735],"iteration":512,"passed_time":0.7483232714,"remaining_time":0.7103965559},
{"learn":[3.882101231],"iteration":513,"passed_time":0.74925266,"remaining_time":0.70843734},
{"learn":[3.88060368],"iteration":514,"passed_time":0.7502261333,"remaining_time":0.7065236401},
{"learn":[3.877726076],"iteration":515,"passed_time":0.751180119,"remaining_time":0.7045953054},
{"learn":[3.874938145],"iteration":516,"passed_time":0.7521484043,"remaining_time":0.7026840992},
{"learn":[3.874340833],"iteration":517,"passed_time":0.7530690043,"remaining_time":0.7007321623},
{"learn":[3.873105224],"iteration":518,"passed_time":0.7540675368,"remaining_time":0.6988564262},
{"learn":[3.869800236],"iteration":519,"passed_time":0.7550766998,"remaining_time":0.6969938767},
{"learn":[3.867932518],"iteration":520,"passed_time":0.7560637242,"remaining_time":0.6951142494},
{"learn":[3.866666962],"iteration":521,"passed_time":0.7570043183,"remaining_time":0.6931955252},
{"learn":[3.865527652],"iteration":522,"passed_time":0.7579834974,"remaining_time":0.6913157328},
{"learn":[3.861900081],"iteration":523,"passed_time":0.7589717135,"remaining_time":0.6894475871},
{"learn":[3.858502887],"iteration":524,"passed_time":0.7599534209,"remaining_time":0.6875769046},
{"learn":[3.858335097],"iteration":525,"passed_time":0.7609296918,"remaining_time":0.6857047032},
{"learn":[3.855719306],"iteration":526,"passed_time":0.7619092299,"remaining_time":0.6838388344},
{"learn":[3.855137428],"iteration":527,"passed_time":0.7628866395,"remaining_time":0.6819744202},
{"learn":[3.851985706],"iteration":528,"passed_time":0.763876391,"remaining_time":0.6801243482},
{"learn":[3.851051809],"iteration":529,"passed_time":0.76483675,"remaining_time":0.6782514576},
{"learn":[3.850679146],"iteration":530,"passed_time":0.7658090365,"remaining_time":0.6763925389},
{"learn":[3.848179484],"iteration":531,"passed_time":0.7667841118,"remaining_time":0.6745394066},
{"learn":[3.844551071],"iteration":532,"passed_time":0.7678197776,"remaining_time":0.672742657},
{"learn":[3.841604794],"iteration":533,"passed_time":0.7688041336,"remaining_time":0.6709039817},
{"learn":[3.83969656],"iteration":534,"passed_time":0.7697828775,"remaining_time":0.6690636225},
{"learn":[3.836811463],"iteration":535,"passed_time":0.7707240173,"remaining_time":0.6671939254},
{"learn":[3.834182551],"iteration":536,"passed_time":0.7716816965,"remaining_time":0.6653419469},
{"learn":[3.828012842],"iteration":537,"passed_time":0.7726402764,"remaining_time":0.6634940664},
{"learn":[3.826636176],"iteration":538,"passed_time":0.773614237,"remaining_time":0.6616626405},
{"learn":[3.826189798],"iteration":539,"passed_time":0.774526897,"remaining_time":0.6597821715},
{"learn":[3.824104738],"iteration":540,"passed_time":0.7754899702,"remaining_time":0.6579480524},
{"learn":[3.82300218],"iteration":541,"passed_time":0.7764326823,"remaining_time":0.6560999419},
{"learn":[3.817146402],"iteration":542,"passed_time":0.7773563955,"remaining_time":0.6542391764},
{"learn":[3.814638044],"iteration":543,"passed_time":0.7783018227,"remaining_time":0.6524000572},
{"learn":[3.812979573],"iteration":544,"passed_time":0.7792534451,"remaining_time":0.65056939},
{"learn":[3.811938825],"iteration":545,"passed_time":0.7802273031,"remaining_time":0.6487604315},
{"learn":[3.811479418],"iteration":546,"passed_time":0.7811493343,"remaining_time":0.6469116059},
{"learn":[3.80742981],"iteration":547,"passed_time":0.7821339783,"remaining_time":0.6451178069},
{"learn":[3.805097043],"iteration":548,"passed_time":0.7831188856,"remaining_time":0.6433271719},
{"learn":[3.801577232],"iteration":549,"passed_time":0.7840922491,"remaining_time":0.641530022},
{"learn":[3.799762083],"iteration":550,"passed_time":0.7850640164,"remaining_time":0.6397345614},
{"learn":[3.796393455],"iteration":551,"passed_time":0.7860649774,"remaining_time":0.6379657788},
{"learn":[3.793486459],"iteration":552,"passed_time":0.7869908519,"remaining_time":0.6361390792},
{"learn":[3.792006091],"iteration":553,"passed_time":0.7880154004,"remaining_time":0.6343950696},
{"learn":[3.78932128],"iteration":554,"passed_time":0.7889990463,"remaining_time":0.6326208569},
{"learn":[3.787581812],"iteration":555,"passed_time":0.7899826297,"remaining_time":0.6308494381},
{"learn":[3.785308865],"iteration":556,"passed_time":0.7909343251,"remaining_time":0.6290554866},
{"learn":[3.78465475],"iteration":557,"passed_time":0.7918498476,"remaining_time":0.6272359008},
{"learn":[3.780498869],"iteration":558,"passed_time":0.7928639134,"remaining_time":0.6254972912},
{"learn":[3.778734909],"iteration":559,"passed_time":0.7938103686,"remaining_time":0.6237081468},
{"learn":[3.778652349],"iteration":560,"passed_time":0.7947135829,"remaining_time":0.6218881692},
{"learn":[3.777928006],"iteration":561,"passed_time":0.7956710049,"remaining_time":0.6201137013},
{"learn":[3.776131406],"iteration":562,"passed_time":0.7967490843,"remaining_time":0.6184357901},
{"learn":[3.772925617],"iteration":563,"passed_time":0.7977026252,"remaining_time":0.6166637316},
{"learn":[3.7727745],"iteration":564,"passed_time":0.798630879,"remaining_time":0.6148751016},
{"learn":[3.771763073],"iteration":565,"passed_time":0.7996061619,"remaining_time":0.6131255729},
{"learn":[3.768738162],"iteration":566,"passed_time":0.8005915211,"remaining_time":0.6113864702},
{"learn":[3.767220794],"iteration":567,"passed_time":0.8015447495,"remaining_time":0.6096255841},
{"learn":[3.766691102],"iteration":568,"passed_time":0.8025113551,"remaining_time":0.6078776697},
{"learn":[3.766259335],"iteration":569,"passed_time":0.8034495851,"remaining_time":0.6061110905},
{"learn":[3.76116362],"iteration":570,"passed_time":0.804442095,"remaining_time":0.6043881939},
{"learn":[3.758633056],"iteration":571,"passed_time":0.8054084305,"remaining_time":0.6026482662},
{"learn":[3.754603809],"iteration":572,"passed_time":0.8063984257,"remaining_time":0.6009286697},
{"learn":[3.754070549],"iteration":573,"passed_time":0.8073732108,"remaining_time":0.5992003272},
{"learn":[3.750534319],"iteration":574,"passed_time":0.8083530158,"remaining_time":0.597478316},
{"learn":[3.746491516],"iteration":575,"passed_time":0.8092987314,"remaining_time":0.5957337884},
{"learn":[3.744210544],"iteration":576,"passed_time":0.8102902435,"remaining_time":0.5940256031},
{"learn":[3.742929991],"iteration":577,"passed_time":0.8112815368,"remaining_time":0.592319738},
{"learn":[3.740402992],"iteration":578,"passed_time":0.8122590859,"remaining_time":0.5906063475},
{"learn":[3.739644243],"iteration":579,"passed_time":0.8131702145,"remaining_time":0.5888473967},
{"learn":[3.737529404],"iteration":580,"passed_time":0.8141597425,"remaining_time":0.5871479038},
{"learn":[3.737196923],"iteration":581,"passed_time":0.8151293668,"remaining_time":0.5854365556},
{"learn":[3.733954464],"iteration":582,"passed_time":0.81614473,"remaining_time":0.5837604673},
{"learn":[3.731608623],"iteration":583,"passed_time":0.8170774338,"remaining_time":0.5820277611},
{"learn":[3.729843952],"iteration":584,"passed_time":0.8180637779,"remaining_time":0.5803358425},
{"learn":[3.727223798],"iteration":585,"passed_time":0.8190677505,"remaining_time":0.5786587862},
{"learn":[3.725351667],"iteration":586,"passed_time":0.8200905007,"remaining_time":0.5769972347},
{"learn":[3.725026912],"iteration":587,"passed_time":0.8210314842,"remaining_time":0.5752805638},
{"learn":[3.721974565],"iteration":588,"passed_time":0.8220355538,"remaining_time":0.5736105477},
{"learn":[3.720269493],"iteration":589,"passed_time":0.8229759771,"remaining_time":0.5718985604},
{"learn":[3.718907466],"iteration":590,"passed_time":0.8238993242,"remaining_time":0.5701773665},
{"learn":[3.715602912],"iteration":591,"passed_time":0.8248872478,"remaining_time":0.5685033735},
{"learn":[3.714463059],"iteration":592,"passed_time":0.8257956125,"remaining_time":0.5667770898},
{"learn":[3.710802077],"iteration":593,"passed_time":0.8267659228,"remaining_time":0.5650959001},
{"learn":[3.708032435],"iteration":594,"passed_time":0.8277233848,"remaining_time":0.5634083544},
{"learn":[3.703788939],"iteration":595,"passed_time":0.8287469468,"remaining_time":0.5617680646},
{"learn":[3.702500944],"iteration":596,"passed_time":0.8297082506,"remaining_time":0.5600878141},
{"learn":[3.698196925],"iteration":597,"passed_time":0.8306602698,"remaining_time":0.5584037265},
{"learn":[3.69658891],"iteration":598,"passed_time":0.831593456,"remaining_time":0.5567094755},
{"learn":[3.696124066],"iteration":599,"passed_time":0.8325789803,"remaining_time":0.5550526535},
{"learn":[3.693537052],"iteration":600,"passed_time":0.8335054014,"remaining_time":0.5533588272},
{"learn":[3.691343275],"iteration":601,"passed_time":0.8344763159,"remaining_time":0.5516969664},
{"learn":[3.690973831],"iteration":602,"passed_time":0.8354333797,"remaining_time":0.5500282782},
{"learn":[3.686151073],"iteration":603,"passed_time":0.8363898096,"remaining_time":0.5483615308},
{"learn":[3.683921982],"iteration":604,"passed_time":0.837363206,"remaining_time":0.5467082089},
{"learn":[3.679975271],"iteration":605,"passed_time":0.8382785418,"remaining_time":0.5450193819},
{"learn":[3.674047638],"iteration":606,"passed_time":0.8391866788,"remaining_time":0.5433284428},
{"learn":[3.673151794],"iteration":607,"passed_time":0.8401442531,"remaining_time":0.5416719526},
{"learn":[3.670953108],"iteration":608,"passed_time":0.841100235,"remaining_time":0.5400167354},
{"learn":[3.6703947],"iteration":609,"passed_time":0.8420574983,"remaining_time":0.53836463},
{"learn":[3.668433805],"iteration":610,"passed_time":0.8430424095,"remaining_time":0.5367324015},
{"learn":[3.668304956],"iteration":611,"passed_time":0.8439809321,"remaining_time":0.5350728785},
{"learn":[3.667880012],"iteration":612,"passed_time":0.8449668001,"remaining_time":0.5334455981},
{"learn":[3.667282264],"iteration":613,"passed_time":0.8459379623,"remaining_time":0.531811162},
{"learn":[3.664611483],"iteration":614,"passed_time":0.8469077133,"remaining_time":0.5301779994},
{"learn":[3.662543394],"iteration":615,"passed_time":0.8478818895,"remaining_time":0.5285497493},
{"learn":[3.659041959],"iteration":616,"passed_time":0.8488533843,"remaining_time":0.5269219549},
{"learn":[3.656868545],"iteration":617,"passed_time":0.8498527129,"remaining_time":0.5253134892},
{"learn":[3.654785614],"iteration":618,"passed_time":0.8508453237,"remaining_time":0.5237028567},
{"learn":[3.654566096],"iteration":619,"passed_time":0.8517858544,"remaining_time":0.5220622979},
{"learn":[3.651007045],"iteration":620,"passed_time":0.8528443336,"remaining_time":0.5204959781},
{"learn":[3.648921786],"iteration":621,"passed_time":0.8538332188,"remaining_time":0.5188889979},
{"learn":[3.647655706],"iteration":622,"passed_time":0.8547633518,"remaining_time":0.5172484489},
{"learn":[3.647241144],"iteration":623,"passed_time":0.8557366889,"remaining_time":0.51563621},
{"learn":[3.644195689],"iteration":624,"passed_time":0.8567131065,"remaining_time":0.5140278639},
{"learn":[3.642632246],"iteration":625,"passed_time":0.8576527205,"remaining_time":0.5123995487},
{"learn":[3.642523322],"iteration":626,"passed_time":0.8583872519,"remaining_time":0.5106514273},
{"learn":[3.641494659],"iteration":627,"passed_time":0.8593831138,"remaining_time":0.5090613349},
{"learn":[3.63976496],"iteration":628,"passed_time":0.8603344318,"remaining_time":0.5074468588},
{"learn":[3.637945652],"iteration":629,"passed_time":0.8613209562,"remaining_time":0.5058551647},
{"learn":[3.636233667],"iteration":630,"passed_time":0.8622851216,"remaining_time":0.5042523136},
{"learn":[3.635304404],"iteration":631,"passed_time":0.8632361912,"remaining_time":0.5026438581},
{"learn":[3.632234951],"iteration":632,"passed_time":0.8641960637,"remaining_time":0.5010425835},
{"learn":[3.631630987],"iteration":633,"passed_time":0.865147348,"remaining_time":0.4994383744},
{"learn":[3.630301009],"iteration":634,"passed_time":0.8661084971,"remaining_time":0.497841892},
{"learn":[3.629077964],"iteration":635,"passed_time":0.86703454,"remaining_time":0.4962273153},
{"learn":[3.628004522],"iteration":636,"passed_time":0.8680388194,"remaining_time":0.4946594842},
{"learn":[3.625062876],"iteration":637,"passed_time":0.8690306329,"remaining_time":0.4930863466},
{"learn":[3.624917986],"iteration":638,"passed_time":0.8699671536,"remaining_time":0.491483791},
{"learn":[3.622887087],"iteration":639,"passed_time":0.8709186478,"remaining_time":0.4898917394},
{"learn":[3.621220865],"iteration":640,"passed_time":0.8718902468,"remaining_time":0.4883129463},
{"learn":[3.621143844],"iteration":641,"passed_time":0.8727728611,"remaining_time":0.4866864241},
{"learn":[3.620822821],"iteration":642,"passed_time":0.8736863017,"remaining_time":0.4850793308},
{"learn":[3.619202826],"iteration":643,"passed_time":0.8746364729,"remaining_time":0.4834946962},
{"learn":[3.618204882],"iteration":644,"passed_time":0.8756068489,"remaining_time":0.4819231494},
{"learn":[3.614259666],"iteration":645,"passed_time":0.8765765326,"remaining_time":0.4803530844},
{"learn":[3.613415661],"iteration":646,"passed_time":0.8775654868,"remaining_time":0.4787953892},
{"learn":[3.611096773],"iteration":647,"passed_time":0.8785399218,"remaining_time":0.4772315624},
{"learn":[3.610820695],"iteration":648,"passed_time":0.879470542,"remaining_time":0.4756458555},
{"learn":[3.609290065],"iteration":649,"passed_time":0.8804442365,"remaining_time":0.4740853581},
{"learn":[3.60897947],"iteration":650,"passed_time":0.8813195985,"remaining_time":0.4724739476},
{"learn":[3.606570702],"iteration":651,"passed_time":0.8822576434,"remaining_time":0.4708982514},
{"learn":[3.606292637],"iteration":652,"passed_time":0.88322573,"remaining_time":0.4693404721},
{"learn":[3.602753838],"iteration":653,"passed_time":0.8842312412,"remaining_time":0.4678042958},
{"learn":[3.599755869],"iteration":654,"passed_time":0.8851594758,"remaining_time":0.4662290368},
{"learn":[3.599509575],"iteration":655,"passed_time":0.8861115871,"remaining_time":0.4646682713},
{"learn":[3.595337722],"iteration":656,"passed_time":0.8870670938,"remaining_time":0.4631111311},
{"learn":[3.595168561],"iteration":657,"passed_time":0.8879903222,"remaining_time":0.4615390428},
{"learn":[3.59290559],"iteration":658,"passed_time":0.8889604747,"remaining_time":0.4599932046},
{"learn":[3.592015928],"iteration":659,"passed_time":0.8899504762,"remaining_time":0.4584593362},
{"learn":[3.590680403],"iteration":660,"passed_time":0.8908609805,"remaining_time":0.4568863425},
{"learn":[3.590361532],"iteration":661,"passed_time":0.8918170306,"remaining_time":0.4553386047},
{"learn":[3.589069739],"iteration":662,"passed_time":0.892802627,"remaining_time":0.4538076701},
{"learn":[3.585010186],"iteration":663,"passed_time":0.893741813,"remaining_time":0.4522548933},
{"learn":[3.582997552],"iteration":664,"passed_time":0.8947168883,"remaining_time":0.4507220415},
{"learn":[3.582119256],"iteration":665,"passed_time":0.8956056908,"remaining_time":0.4491475987},
{"learn":[3.579019356],"iteration":666,"passed_time":0.8966463965,"remaining_time":0.4476510495},
{"learn":[3.57719559],"iteration":667,"passed_time":0.8975892207,"remaining_time":0.4461072175},
{"learn":[3.574050046],"iteration":668,"passed_time":0.8985685513,"remaining_time":0.4445832443},
{"learn":[3.572204518],"iteration":669,"passed_time":0.899544129,"remaining_time":0.4430590486},
{"learn":[3.569508025],"iteration":670,"passed_time":0.9005427492,"remaining_time":0.4415477861},
{"learn":[3.566268704],"iteration":671,"passed_time":0.9015205187,"remaining_time":0.4400278722},
{"learn":[3.562564052],"iteration":672,"passed_time":0.9025142891,"remaining_time":0.438517344},
{"learn":[3.561173586],"iteration":673,"passed_time":0.9034868945,"remaining_time":0.4369981122},
{"learn":[3.559551904],"iteration":674,"passed_time":0.9044126128,"remaining_time":0.4354579247},
{"learn":[3.558593054],"iteration":675,"passed_time":0.9054068816,"remaining_time":0.4339524107},
{"learn":[3.555647008],"iteration":676,"passed_time":0.9063944102,"remaining_time":0.4324451913},
{"learn":[3.553100059],"iteration":677,"passed_time":0.9073689277,"remaining_time":0.4309333255},
{"learn":[3.55085578],"iteration":678,"passed_time":0.9083652272,"remaining_time":0.4294333401},
{"learn":[3.550737965],"iteration":679,"passed_time":0.909590966,"remaining_time":0.4280428075},
{"learn":[3.549408772],"iteration":680,"passed_time":0.9126687906,"remaining_time":0.4275203292},
{"learn":[3.547390589],"iteration":681,"passed_time":0.9158554948,"remaining_time":0.4270411252},
{"learn":[3.54723575],"iteration":682,"passed_time":0.918497314,"remaining_time":0.426301096},
{"learn":[3.543988891],"iteration":683,"passed_time":0.9216250765,"remaining_time":0.4257800061},
{"learn":[3.543868508],"iteration":684,"passed_time":0.9257644787,"remaining_time":0.4257165121},
{"learn":[3.542752124],"iteration":685,"passed_time":0.9290668234,"remaining_time":0.4252579921},
{"learn":[3.541334315],"iteration":686,"passed_time":0.9319933054,"remaining_time":0.4246199485},
{"learn":[3.540208266],"iteration":687,"passed_time":0.9348088441,"remaining_time":0.4239249409},
{"learn":[3.537730983],"iteration":688,"passed_time":0.9376048672,"remaining_time":0.4232149691},
{"learn":[3.53419867],"iteration":689,"passed_time":0.940351542,"remaining_time":0.4224767797},
{"learn":[3.532628335],"iteration":690,"passed_time":0.9430870546,"remaining_time":0.4217277857},
{"learn":[3.532204987],"iteration":691,"passed_time":0.9459041905,"remaining_time":0.4210093796},
{"learn":[3.530618147],"iteration":692,"passed_time":0.9485822884,"remaining_time":0.4202233226},
{"learn":[3.528909306],"iteration":693,"passed_time":0.9513194494,"remaining_time":0.4194578552},
{"learn":[3.526700678],"iteration":694,"passed_time":0.954162955,"remaining_time":0.4187333831},
{"learn":[3.526439574],"iteration":695,"passed_time":0.9568595252,"remaining_time":0.4179386432},
{"learn":[3.525784216],"iteration":696,"passed_time":0.9595707468,"remaining_time":0.4171448153},
{"learn":[3.524112693],"iteration":697,"passed_time":0.9623925755,"remaining_time":0.4163933493},
{"learn":[3.522813541],"iteration":698,"passed_time":0.9652030327,"remaining_time":0.4156310627},
{"learn":[3.519148203],"iteration":699,"passed_time":0.9680299477,"remaining_time":0.4148699776},
{"learn":[3.517236747],"iteration":700,"passed_time":0.9707233573,"remaining_time":0.414046054},
{"learn":[3.515603888],"iteration":701,"passed_time":0.9736428133,"remaining_time":0.4133127612},
{"learn":[3.51263524],"iteration":702,"passed_time":0.9764207999,"remaining_time":0.4125134816},
{"learn":[3.51123442],"iteration":703,"passed_time":0.9791669483,"remaining_time":0.4116951942},
{"learn":[3.50828027],"iteration":704,"passed_time":0.9820127426,"remaining_time":0.4109131334},
{"learn":[3.508265537],"iteration":705,"passed_time":0.9836535078,"remaining_time":0.4096234154},
{"learn":[3.506774876],"iteration":706,"passed_time":0.9864164641,"remaining_time":0.4087977708},
{"learn":[3.50552068],"iteration":707,"passed_time":0.9891963981,"remaining_time":0.4079736557},
{"learn":[3.501973993],"iteration":708,"passed_time":0.9920288072,"remaining_time":0.4071655612},
{"learn":[3.498880354],"iteration":709,"passed_time":0.9949013279,"remaining_time":0.406368148},
{"learn":[3.497370959],"iteration":710,"passed_time":0.997587437,"remaining_time":0.405489127},
{"learn":[3.496050455],"iteration":711,"passed_time":1.000311911,"remaining_time":0.4046205482},
{"learn":[3.495630067],"iteration":712,"passed_time":1.003398167,"remaining_time":0.4038923899},
{"learn":[3.49550669],"iteration":713,"passed_time":1.006247245,"remaining_time":0.4030626219},
{"learn":[3.493652375],"iteration":714,"passed_time":1.009255922,"remaining_time":0.4022908222},
{"learn":[3.491915684],"iteration":715,"passed_time":1.011988882,"remaining_time":0.4014034112},
{"learn":[3.490303956],"iteration":716,"passed_time":1.014871953,"remaining_time":0.4005701015},
{"learn":[3.488363853],"iteration":717,"passed_time":1.017772042,"remaining_time":0.3997377657},
{"learn":[3.485483936],"iteration":718,"passed_time":1.020496834,"remaining_time":0.3988311687},
{"learn":[3.483763466],"iteration":719,"passed_time":1.022496879,"remaining_time":0.3976376752},
{"learn":[3.481642352],"iteration":720,"passed_time":1.024496431,"remaining_time":0.3964417536},
{"learn":[3.479826119],"iteration":721,"passed_time":1.026605667,"remaining_time":0.3952858385},
{"learn":[3.478588728],"iteration":722,"passed_time":1.02852313,"remaining_time":0.3940538132},
{"learn":[3.475390887],"iteration":723,"passed_time":1.030017636,"remaining_time":0.3926586568},
{"learn":[3.472636852],"iteration":724,"passed_time":1.03157503,"remaining_time":0.3912870804},
{"learn":[3.47061883],"iteration":725,"passed_time":1.033091699,"remaining_time":0.3898996219},
{"learn":[3.46953149],"iteration":726,"passed_time":1.034627184,"remaining_time":0.3885188739},
{"learn":[3.467217162],"iteration":727,"passed_time":1.036154717,"remaining_time":0.3871347295},
{"learn":[3.465686216],"iteration":728,"passed_time":1.037588287,"remaining_time":0.3857152616},
{"learn":[3.462631216],"iteration":729,"passed_time":1.038864062,"remaining_time":0.3842373928},
{"learn":[3.461451053],"iteration":730,"passed_time":1.040107925,"remaining_time":0.3827483334},
{"learn":[3.458950469],"iteration":731,"passed_time":1.041357797,"remaining_time":0.3812621444},
{"learn":[3.458072145],"iteration":732,"passed_time":1.042589331,"remaining_time":0.37976992},
{"learn":[3.454364268],"iteration":733,"passed_time":1.043845462,"remaining_time":0.3782873199},
{"learn":[3.453243406],"iteration":734,"passed_time":1.04497475,"remaining_time":0.3767596036},
{"learn":[3.453017963],"iteration":735,"passed_time":1.045974873,"remaining_time":0.3751866393},
{"learn":[3.45201581],"iteration":736,"passed_time":1.047043693,"remaining_time":0.373639744},
{"learn":[3.449510107],"iteration":737,"passed_time":1.048126862,"remaining_time":0.3720992384},
{"learn":[3.447189189],"iteration":738,"passed_time":1.049195485,"remaining_time":0.3705548328},
{"learn":[3.446423605],"iteration":739,"passed_time":1.050221177,"remaining_time":0.3689966296},
{"learn":[3.445531987],"iteration":740,"passed_time":1.051224157,"remaining_time":0.3674319253},
{"learn":[3.445328199],"iteration":741,"passed_time":1.052231532,"remaining_time":0.3658702632},
{"learn":[3.443327544],"iteration":742,"passed_time":1.05321215,"remaining_time":0.3643008378},
{"learn":[3.441475798],"iteration":743,"passed_time":1.054196093,"remaining_time":0.3627341395},
{"learn":[3.439046501],"iteration":744,"passed_time":1.055149738,"remaining_time":0.3611586352},
{"learn":[3.435899469],"iteration":745,"passed_time":1.056074977,"remaining_time":0.3595751263},
{"learn":[3.433988352],"iteration":746,"passed_time":1.057031616,"remaining_time":0.3580040146},
{"learn":[3.433413263],"iteration":747,"passed_time":1.057976583,"remaining_time":0.3564306136},
{"learn":[3.429944699],"iteration":748,"passed_time":1.058973569,"remaining_time":0.3548763228},
{"learn":[3.429291634],"iteration":749,"passed_time":1.05995267,"remaining_time":0.3533175567},
{"learn":[3.429175603],"iteration":750,"passed_time":1.06089697,"remaining_time":0.3517487955},
{"learn":[3.428780323],"iteration":751,"passed_time":1.061820676,"remaining_time":0.3501749039},
{"learn":[3.423893341],"iteration":752,"passed_time":1.062804241,"remaining_time":0.348622374},
{"learn":[3.421024316],"iteration":753,"passed_time":1.063835685,"remaining_time":0.3470869742},
{"learn":[3.420969872],"iteration":754,"passed_time":1.064782246,"remaining_time":0.3455253644},
{"learn":[3.419544785],"iteration":755,"passed_time":1.065777275,"remaining_time":0.3439810252},
{"learn":[3.417057977],"iteration":756,"passed_time":1.066746184,"remaining_time":0.3424297525},
{"learn":[3.415160245],"iteration":757,"passed_time":1.067756371,"remaining_time":0.340893195},
{"learn":[3.412854597],"iteration":758,"passed_time":1.068764592,"remaining_time":0.3393574},
{"learn":[3.410926347],"iteration":759,"passed_time":1.069740859,"remaining_time":0.3378129027},
{"learn":[3.408963843],"iteration":760,"passed_time":1.070687481,"remaining_time":0.3362605885},
{"learn":[3.407629634],"iteration":761,"passed_time":1.071664094,"remaining_time":0.3347192314},
{"learn":[3.404384724],"iteration":762,"passed_time":1.072638707,"remaining_time":0.3331787335},
{"learn":[3.403041656],"iteration":763,"passed_time":1.073659289,"remaining_time":0.3316539165},
{"learn":[3.401101731],"iteration":764,"passed_time":1.074646081,"remaining_time":0.330120038},
{"learn":[3.400890668],"iteration":765,"passed_time":1.075583872,"remaining_time":0.3285726189},
{"learn":[3.399289941],"iteration":766,"passed_time":1.076558846,"remaining_time":0.327038085},
{"learn":[3.399202366],"iteration":767,"passed_time":1.077451465,"remaining_time":0.32548013},
{"learn":[3.397447845],"iteration":768,"passed_time":1.078398117,"remaining_time":0.3239401367},
{"learn":[3.394655341],"iteration":769,"passed_time":1.079391929,"remaining_time":0.3224157709},
{"learn":[3.393228229],"iteration":770,"passed_time":1.080363199,"remaining_time":0.3208860863},
{"learn":[3.389691197],"iteration":771,"passed_time":1.081353236,"remaining_time":0.3193633909},
{"learn":[3.389626772],"iteration":772,"passed_time":1.082296878,"remaining_time":0.3178284494},
{"learn":[3.388480222],"iteration":773,"passed_time":1.083255182,"remaining_time":0.3162993166},
{"learn":[3.388215066],"iteration":774,"passed_time":1.084271012,"remaining_time":0.3147883584},
{"learn":[3.386324358],"iteration":775,"passed_time":1.085245354,"remaining_time":0.3132667002},
{"learn":[3.383913061],"iteration":776,"passed_time":1.086231088,"remaining_time":0.3117497201},
{"learn":[3.382839768],"iteration":777,"passed_time":1.087210582,"remaining_time":0.3102323256},
{"learn":[3.381961844],"iteration":778,"passed_time":1.088164717,"remaining_time":0.3087091175},
{"learn":[3.381521703],"iteration":779,"passed_time":1.089151295,"remaining_time":0.3071965192},
{"learn":[3.380918963],"iteration":780,"passed_time":1.090121498,"remaining_time":0.3056806762},
{"learn":[3.377139006],"iteration":781,"passed_time":1.091109728,"remaining_time":0.3041712541},
{"learn":[3.376004372],"iteration":782,"passed_time":1.092069831,"remaining_time":0.3026553683},
{"learn":[3.373826468],"iteration":783,"passed_time":1.093031379,"remaining_time":0.3011412982},
{"learn":[3.373546786],"iteration":784,"passed_time":1.093973438,"remaining_time":0.2996232984},
{"learn":[3.372109181],"iteration":785,"passed_time":1.0949574,"remaining_time":0.2981181725},
{"learn":[3.370764924],"iteration":786,"passed_time":1.095936416,"remaining_time":0.2966130325},
{"learn":[3.367833107],"iteration":787,"passed_time":1.09691269,"remaining_time":0.2951084902},
{"learn":[3.36450404],"iteration":788,"passed_time":1.097875797,"remaining_time":0.2936017659},
{"learn":[3.361794558],"iteration":789,"passed_time":1.098855108,"remaining_time":0.2921007249},
{"learn":[3.356880529],"iteration":790,"passed_time":1.099852122,"remaining_time":0.2906056809},
{"learn":[3.353843509],"iteration":791,"passed_time":1.100813311,"remaining_time":0.2891024856},
{"learn":[3.353640253],"iteration":792,"passed_time":1.101733786,"remaining_time":0.28759003},
{"learn":[3.353055088],"iteration":793,"passed_time":1.102659188,"remaining_time":0.2860803435},
{"learn":[3.351415617],"iteration":794,"passed_time":1.103630172,"remaining_time":0.2845838807},
{"learn":[3.349169061],"iteration":795,"passed_time":1.104551772,"remaining_time":0.2830760822},
{"learn":[3.346211014],"iteration":796,"passed_time":1.105504272,"remaining_time":0.2815776252},
{"learn":[3.344560452],"iteration":797,"passed_time":1.10650043,"remaining_time":0.2800915876},
{"learn":[3.344445461],"iteration":798,"passed_time":1.107462994,"remaining_time":0.2785983253},
{"learn":[3.342608898],"iteration":799,"passed_time":1.108478441,"remaining_time":0.2771196103},
{"learn":[3.339572899],"iteration":800,"passed_time":1.109457692,"remaining_time":0.2756330596},
{"learn":[3.339309302],"iteration":801,"passed_time":1.110362492,"remaining_time":0.2741293934},
{"learn":[3.33698088],"iteration":802,"passed_time":1.111336817,"remaining_time":0.2726442751},
{"learn":[3.334746342],"iteration":803,"passed_time":1.112303182,"remaining_time":0.2711584872},
{"learn":[3.332048511],"iteration":804,"passed_time":1.113263769,"remaining_time":0.2696725899},
{"learn":[3.331932544],"iteration":805,"passed_time":1.114189904,"remaining_time":0.2681797038},
{"learn":[3.330541133],"iteration":806,"passed_time":1.115147101,"remaining_time":0.2666956512},
{"learn":[3.329124989],"iteration":807,"passed_time":1.116089418,"remaining_time":0.2652093667},
{"learn":[3.32583918],"iteration":808,"passed_time":1.117024505,"remaining_time":0.26372272},
{"learn":[3.325287299],"iteration":809,"passed_time":1.117992847,"remaining_time":0.2622452358},
{"learn":[3.322745162],"iteration":810,"passed_time":1.11891976,"remaining_time":0.2607593521},
{"learn":[3.319733662],"iteration":811,"passed_time":1.119908381,"remaining_time":0.2592891326},
{"learn":[3.318080007],"iteration":812,"passed_time":1.120818416,"remaining_time":0.2578020219},
{"learn":[3.317179538],"iteration":813,"passed_time":1.121777261,"remaining_time":0.2563274823},
{"learn":[3.315685949],"iteration":814,"passed_time":1.122727914,"remaining_time":0.2548523486},
{"learn":[3.314944576],"iteration":815,"passed_time":1.123704824,"remaining_time":0.253384421},
{"learn":[3.312369052],"iteration":816,"passed_time":1.124694164,"remaining_time":0.2519204798},
{"learn":[3.312321621],"iteration":817,"passed_time":1.125453341,"remaining_time":0.250406489},
{"learn":[3.309465776],"iteration":818,"passed_time":1.126510755,"remaining_time":0.2489602524},
{"learn":[3.308307377],"iteration":819,"passed_time":1.127462979,"remaining_time":0.2474918734},
{"learn":[3.308076804],"iteration":820,"passed_time":1.12836026,"remaining_time":0.246012773},
{"learn":[3.305643326],"iteration":821,"passed_time":1.12932678,"remaining_time":0.2445500814},
{"learn":[3.304154814],"iteration":822,"passed_time":1.130260368,"remaining_time":0.2430815129},
{"learn":[3.303076321],"iteration":823,"passed_time":1.131247689,"remaining_time":0.24162572},
{"learn":[3.301746372],"iteration":824,"passed_time":1.132216127,"remaining_time":0.2401670573},
{"learn":[3.301345455],"iteration":825,"passed_time":1.133139508,"remaining_time":0.2387000901},
{"learn":[3.299181039],"iteration":826,"passed_time":1.134099239,"remaining_time":0.2372420415},
{"learn":[3.297989357],"iteration":827,"passed_time":1.135061985,"remaining_time":0.235785823},
{"learn":[3.294775182],"iteration":828,"passed_time":1.13606438,"remaining_time":0.2343389734},
{"learn":[3.293840636],"iteration":829,"passed_time":1.137016117,"remaining_time":0.2328828191},
{"learn":[3.289279397],"iteration":830,"passed_time":1.137979608,"remaining_time":0.2314302693},
{"learn":[3.286204979],"iteration":831,"passed_time":1.138964367,"remaining_time":0.2299831894},
{"learn":[3.284833593],"iteration":832,"passed_time":1.139977024,"remaining_time":0.2285428128},
{"learn":[3.283519914],"iteration":833,"passed_time":1.140955703,"remaining_time":0.2270966987},
{"learn":[3.282853026],"iteration":834,"passed_time":1.141964579,"remaining_time":0.2256576714},
{"learn":[3.281944673],"iteration":835,"passed_time":1.142917904,"remaining_time":0.2242087754},
{"learn":[3.279764865],"iteration":836,"passed_time":1.14389965,"remaining_time":0.2227665985},
{"learn":[3.277468839],"iteration":837,"passed_time":1.144900402,"remaining_time":0.2213291946},
{"learn":[3.277124974],"iteration":838,"passed_time":1.145811223,"remaining_time":0.2198755743},
{"learn":[3.275636037],"iteration":839,"passed_time":1.146796288,"remaining_time":0.2184373881},
{"learn":[3.274413635],"iteration":840,"passed_time":1.147710028,"remaining_time":0.2169867948},
{"learn":[3.272636087],"iteration":841,"passed_time":1.148651562,"remaining_time":0.2155426922},
{"learn":[3.269644466],"iteration":842,"passed_time":1.149619097,"remaining_time":0.2141046243},
{"learn":[3.26852083],"iteration":843,"passed_time":1.150610109,"remaining_time":0.2126720107},
{"learn":[3.267820927],"iteration":844,"passed_time":1.151565963,"remaining_time":0.2112339932},
{"learn":[3.267331099],"iteration":845,"passed_time":1.152552455,"remaining_time":0.2098026928},
{"learn":[3.267231014],"iteration":846,"passed_time":1.153468786,"remaining_time":0.208359769},
{"learn":[3.267158695],"iteration":847,"passed_time":1.154601135,"remaining_time":0.2069568073},
{"learn":[3.264718705],"iteration":848,"passed_time":1.155634321,"remaining_time":0.2055368462},
{"learn":[3.261678512],"iteration":849,"passed_time":1.156591491,"remaining_time":0.2041043808},
{"learn":[3.261368381],"iteration":850,"passed_time":1.157548423,"remaining_time":0.2026729907},
{"learn":[3.260128799],"iteration":851,"passed_time":1.15851074,"remaining_time":0.2012436497},
{"learn":[3.258972952],"iteration":852,"passed_time":1.159484867,"remaining_time":0.1998174391},
{"learn":[3.258724846],"iteration":853,"passed_time":1.160438895,"remaining_time":0.1983888509},
{"learn":[3.25686724],"iteration":854,"passed_time":1.161446845,"remaining_time":0.1969705175},
{"learn":[3.255750259],"iteration":855,"passed_time":1.162385902,"remaining_time":0.1955415537},
{"learn":[3.254915866],"iteration":856,"passed_time":1.163366953,"remaining_time":0.1941207402},
{"learn":[3.254348625],"iteration":857,"passed_time":1.164289793,"remaining_time":0.1926913178},
{"learn":[3.253408514],"iteration":858,"passed_time":1.165257498,"remaining_time":0.1912704392},
{"learn":[3.253291714],"iteration":859,"passed_time":1.166184653,"remaining_time":0.1898440134},
{"learn":[3.250186342],"iteration":860,"passed_time":1.167155607,"remaining_time":0.1884258181},
{"learn":[3.249141318],"iteration":861,"passed_time":1.168129654,"remaining_time":0.1870091558},
{"learn":[3.246300388],"iteration":862,"passed_time":1.16910368,"remaining_time":0.1855935158},
{"learn":[3.245205135],"iteration":863,"passed_time":1.17007899,"remaining_time":0.1841791003},
{"learn":[3.244403535],"iteration":864,"passed_time":1.171025743,"remaining_time":0.1827612431},
{"learn":[3.244211781],"iteration":865,"passed_time":1.171940199,"remaining_time":0.1813394766},
{"learn":[3.242286347],"iteration":866,"passed_time":1.172892065,"remaining_time":0.179924619},
{"learn":[3.239606746],"iteration":867,"passed_time":1.173822439,"remaining_time":0.1785075598},
{"learn":[3.236773361],"iteration":868,"passed_time":1.174785915,"remaining_time":0.1770966109},
{"learn":[3.234552446],"iteration":869,"passed_time":1.17569961,"remaining_time":0.1756792521},
{"learn":[3.233724647],"iteration":870,"passed_time":1.176646818,"remaining_time":0.1742680133},
{"learn":[3.230851485],"iteration":871,"passed_time":1.177628369,"remaining_time":0.1728628799},
{"learn":[3.227728941],"iteration":872,"passed_time":1.178564505,"remaining_time":0.1714521102},
{"learn":[3.225787575],"iteration":873,"passed_time":1.179539258,"remaining_time":0.1700479937},
{"learn":[3.222797487],"iteration":874,"passed_time":1.180479042,"remaining_time":0.1686398631},
{"learn":[3.22137014],"iteration":875,"passed_time":1.181460577,"remaining_time":0.1672387118},
{"learn":[3.219701963],"iteration":876,"passed_time":1.182447616,"remaining_time":0.1658392894},
{"learn":[3.21783327],"iteration":877,"passed_time":1.183437344,"remaining_time":0.1644411799},
{"learn":[3.217713355],"iteration":878,"passed_time":1.184354132,"remaining_time":0.163033959},
{"learn":[3.217666091],"iteration":879,"passed_time":1.185255549,"remaining_time":0.1616257566},
{"learn":[3.214962005],"iteration":880,"passed_time":1.186214717,"remaining_time":0.1602265054},
{"learn":[3.214081828],"iteration":881,"passed_time":1.187138328,"remaining_time":0.1588234951},
{"learn":[3.213358337],"iteration":882,"passed_time":1.188149769,"remaining_time":0.1574332083},
{"learn":[3.210850401],"iteration":883,"passed_time":1.189109924,"remaining_time":0.1560370489},
{"learn":[3.207810328],"iteration":884,"passed_time":1.190031279,"remaining_time":0.1546368329},
{"learn":[3.204935073],"iteration":885,"passed_time":1.191015162,"remaining_time":0.1532457432},
{"learn":[3.20280198],"iteration":886,"passed_time":1.191998181,"remaining_time":0.1518554616},
{"learn":[3.200663495],"iteration":887,"passed_time":1.192995095,"remaining_time":0.1504678499},
{"learn":[3.197301669],"iteration":888,"passed_time":1.193996663,"remaining_time":0.1490816981},
{"learn":[3.195666943],"iteration":889,"passed_time":1.195034352,"remaining_time":0.1477008749},
{"learn":[3.193886506],"iteration":890,"passed_time":1.195976833,"remaining_time":0.1463091748},
{"learn":[3.190601248],"iteration":891,"passed_time":1.196970699,"remaining_time":0.1449247034},
{"learn":[3.188983797],"iteration":892,"passed_time":1.197948584,"remaining_time":0.1435391921},
{"learn":[3.187365749],"iteration":893,"passed_time":1.198922861,"remaining_time":0.1421541648},
{"learn":[3.186160771],"iteration":894,"passed_time":1.199901805,"remaining_time":0.1407706028},
{"learn":[3.185358981],"iteration":895,"passed_time":1.200851992,"remaining_time":0.1393846062},
{"learn":[3.183832164],"iteration":896,"passed_time":1.201828238,"remaining_time":0.1380025736},
{"learn":[3.183106966],"iteration":897,"passed_time":1.202767964,"remaining_time":0.1366172966},
{"learn":[3.182838152],"iteration":898,"passed_time":1.203705237,"remaining_time":0.1352327352},
{"learn":[3.180835453],"iteration":899,"passed_time":1.204686902,"remaining_time":0.1338541003},
{"learn":[3.179957348],"iteration":900,"passed_time":1.205644897,"remaining_time":0.1324737457},
{"learn":[3.179752966],"iteration":901,"passed_time":1.206575569,"remaining_time":0.1310913589},
{"learn":[3.178851983],"iteration":902,"passed_time":1.207529449,"remaining_time":0.1297124657},
{"learn":[3.176748586],"iteration":903,"passed_time":1.208478084,"remaining_time":0.1283339558},
{"learn":[3.172960988],"iteration":904,"passed_time":1.209473918,"remaining_time":0.1269613505},
{"learn":[3.172794225],"iteration":905,"passed_time":1.210352412,"remaining_time":0.1255774026},
{"learn":[3.169996507],"iteration":906,"passed_time":1.211357577,"remaining_time":0.1242075575},
{"learn":[3.16813015],"iteration":907,"passed_time":1.212308357,"remaining_time":0.1228330053},
{"learn":[3.166920871],"iteration":908,"passed_time":1.2132528,"remaining_time":0.1214587512},
{"learn":[3.16531606],"iteration":909,"passed_time":1.214202212,"remaining_time":0.120085933},
{"learn":[3.162035247],"iteration":910,"passed_time":1.215175542,"remaining_time":0.1187163811},
{"learn":[3.16189467],"iteration":911,"passed_time":1.216064344,"remaining_time":0.1173395419},
{"learn":[3.161008416],"iteration":912,"passed_time":1.217032413,"remaining_time":0.1159713253},
{"learn":[3.160560787],"iteration":913,"passed_time":1.21796958,"remaining_time":0.1146010764},
{"learn":[3.160416261],"iteration":914,"passed_time":1.218888493,"remaining_time":0.1132300786},
{"learn":[3.15844291],"iteration":915,"passed_time":1.219906991,"remaining_time":0.1118692001},
{"learn":[3.155040501],"iteration":916,"passed_time":1.22085749,"remaining_time":0.1105029135},
{"learn":[3.154937548],"iteration":917,"passed_time":1.221815523,"remaining_time":0.1091382058},
{"learn":[3.153721161],"iteration":918,"passed_time":1.22279761,"remaining_time":0.1077765032},
{"learn":[3.153170511],"iteration":919,"passed_time":1.2237934,"remaining_time":0.1064168174},
{"learn":[3.153113601],"iteration":920,"passed_time":1.224705747,"remaining_time":0.1050507644},
{"learn":[3.150607379],"iteration":921,"passed_time":1.225699601,"remaining_time":0.1036925909},
{"learn":[3.148408359],"iteration":922,"passed_time":1.226634289,"remaining_time":0.1023302712},
{"learn":[3.147495728],"iteration":923,"passed_time":1.227626148,"remaining_time":0.1009735793},
{"learn":[3.146946235],"iteration":924,"passed_time":1.228576381,"remaining_time":0.09961430112},
{"learn":[3.14472738],"iteration":925,"passed_time":1.229511277,"remaining_time":0.09825468087},
{"learn":[3.144469477],"iteration":926,"passed_time":1.230426344,"remaining_time":0.09689441545},
{"learn":[3.142975516],"iteration":927,"passed_time":1.231368615,"remaining_time":0.0955372201},
{"learn":[3.14079113],"iteration":928,"passed_time":1.232346617,"remaining_time":0.0941836489},
{"learn":[3.138173032],"iteration":929,"passed_time":1.233315807,"remaining_time":0.092830222},
{"learn":[3.136352813],"iteration":930,"passed_time":1.234293603,"remaining_time":0.0914782584},
{"learn":[3.133735004],"iteration":931,"passed_time":1.235254034,"remaining_time":0.09012583084},
{"learn":[3.1319496],"iteration":932,"passed_time":1.236217604,"remaining_time":0.08877446886},
{"learn":[3.129865343],"iteration":933,"passed_time":1.237169083,"remaining_time":0.08742308299},
{"learn":[3.129830206],"iteration":934,"passed_time":1.23788238,"remaining_time":0.08605599435},
{"learn":[3.126676562],"iteration":935,"passed_time":1.238840091,"remaining_time":0.0847070148},
{"learn":[3.12645665],"iteration":936,"passed_time":1.239793657,"remaining_time":0.08335859168},
{"learn":[3.126378007],"iteration":937,"passed_time":1.240721738,"remaining_time":0.08200932596},
{"learn":[3.124621914],"iteration":938,"passed_time":1.241691181,"remaining_time":0.08066364436},
{"learn":[3.123379018],"iteration":939,"passed_time":1.242660645,"remaining_time":0.07931876455},
{"learn":[3.123332451],"iteration":940,"passed_time":1.243572699,"remaining_time":0.07797108313},
{"learn":[3.122432444],"iteration":941,"passed_time":1.244525165,"remaining_time":0.07662681483},
{"learn":[3.121889006],"iteration":942,"passed_time":1.245508903,"remaining_time":0.07528526774},
{"learn":[3.121070914],"iteration":943,"passed_time":1.246458448,"remaining_time":0.07394245028},
{"learn":[3.118444705],"iteration":944,"passed_time":1.247399535,"remaining_time":0.07259997291},
{"learn":[3.116820458],"iteration":945,"passed_time":1.248392024,"remaining_time":0.07126127834},
{"learn":[3.114971041],"iteration":946,"passed_time":1.249360609,"remaining_time":0.06992197703},
{"learn":[3.114685138],"iteration":947,"passed_time":1.250272147,"remaining_time":0.06858032872},
{"learn":[3.113399363],"iteration":948,"passed_time":1.251288271,"remaining_time":0.06724520738},
{"learn":[3.110575399],"iteration":949,"passed_time":1.25228579,"remaining_time":0.06590977841},
{"learn":[3.110466553],"iteration":950,"passed_time":1.253210003,"remaining_time":0.06457128302},
{"learn":[3.108691641],"iteration":951,"passed_time":1.254168004,"remaining_time":0.06323536153},
{"learn":[3.107898017],"iteration":952,"passed_time":1.255116589,"remaining_time":0.06189976882},
{"learn":[3.105551729],"iteration":953,"passed_time":1.25608953,"remaining_time":0.06056616184},
{"learn":[3.104824945],"iteration":954,"passed_time":1.257051529,"remaining_time":0.05923279455},
{"learn":[3.103186704],"iteration":955,"passed_time":1.258048818,"remaining_time":0.05790182844},
{"learn":[3.102330655],"iteration":956,"passed_time":1.259001957,"remaining_time":0.05656957594},
{"learn":[3.102291298],"iteration":957,"passed_time":1.25986617,"remaining_time":0.05523421622},
{"learn":[3.100363529],"iteration":958,"passed_time":1.26080255,"remaining_time":0.05390292444},
{"learn":[3.097871596],"iteration":959,"passed_time":1.261773974,"remaining_time":0.05257391558},
{"learn":[3.097372213],"iteration":960,"passed_time":1.26276187,"remaining_time":0.0512463194},
{"learn":[3.095981813],"iteration":961,"passed_time":1.263714923,"remaining_time":0.0499180531},
{"learn":[3.095347452],"iteration":962,"passed_time":1.26468506,"remaining_time":0.04859122244},
{"learn":[3.094728409],"iteration":963,"passed_time":1.265698684,"remaining_time":0.04726675583},
{"learn":[3.094118537],"iteration":964,"passed_time":1.266669077,"remaining_time":0.04594136548},
{"learn":[3.093793695],"iteration":965,"passed_time":1.267620392,"remaining_time":0.04461603865},
{"learn":[3.092581602],"iteration":966,"passed_time":1.268559123,"remaining_time":0.04329105591},
{"learn":[3.091694202],"iteration":967,"passed_time":1.269568628,"remaining_time":0.04196921086},
{"learn":[3.090298312],"iteration":968,"passed_time":1.270526028,"remaining_time":0.04064634352},
{"learn":[3.090020107],"iteration":969,"passed_time":1.271449562,"remaining_time":0.03932318232},
{"learn":[3.088949869],"iteration":970,"passed_time":1.272380462,"remaining_time":0.03800106427},
{"learn":[3.086700204],"iteration":971,"passed_time":1.273327428,"remaining_time":0.03668021398},
{"learn":[3.086584317],"iteration":972,"passed_time":1.274253301,"remaining_time":0.0353595469},
{"learn":[3.084850742],"iteration":973,"passed_time":1.275245659,"remaining_time":0.03404146524},
{"learn":[3.084239948],"iteration":974,"passed_time":1.27621215,"remaining_time":0.03272338847},
{"learn":[3.082561673],"iteration":975,"passed_time":1.277175108,"remaining_time":0.03140594529},
{"learn":[3.07991814],"iteration":976,"passed_time":1.278176423,"remaining_time":0.03009013073},
{"learn":[3.079350277],"iteration":977,"passed_time":1.279152678,"remaining_time":0.02877439563},
{"learn":[3.077637462],"iteration":978,"passed_time":1.280176816,"remaining_time":0.02746038114},
{"learn":[3.076733301],"iteration":979,"passed_time":1.281119838,"remaining_time":0.02614530282},
{"learn":[3.07594065],"iteration":980,"passed_time":1.282095113,"remaining_time":0.02483160769},
{"learn":[3.072594655],"iteration":981,"passed_time":1.283062913,"remaining_time":0.02351846481},
{"learn":[3.071977674],"iteration":982,"passed_time":1.284061328,"remaining_time":0.02220655399},
{"learn":[3.069532634],"iteration":983,"passed_time":1.285029505,"remaining_time":0.02089478871},
{"learn":[3.068870784],"iteration":984,"passed_time":1.285983409,"remaining_time":0.0195835037},
{"learn":[3.068801463],"iteration":985,"passed_time":1.286891212,"remaining_time":0.01827228902},
{"learn":[3.067433249],"iteration":986,"passed_time":1.287876266,"remaining_time":0.01696290928},
{"learn":[3.065611456],"iteration":987,"passed_time":1.288865357,"remaining_time":0.0156542351},
{"learn":[3.063039162],"iteration":988,"passed_time":1.289833385,"remaining_time":0.01434597293},
{"learn":[3.06177873],"iteration":989,"passed_time":1.290806143,"remaining_time":0.01303844589},
{"learn":[3.061689148],"iteration":990,"passed_time":1.291710218,"remaining_time":0.0117309707},
{"learn":[3.058984039],"iteration":991,"passed_time":1.292698598,"remaining_time":0.01042498869},
{"learn":[3.057492984],"iteration":992,"passed_time":1.293656391,"remaining_time":0.009119430751},
{"learn":[3.057290731],"iteration":993,"passed_time":1.294619784,"remaining_time":0.00781460634},
{"learn":[3.056068348],"iteration":994,"passed_time":1.295494849,"remaining_time":0.006510024368},
{"learn":[3.054987307],"iteration":995,"passed_time":1.296462457,"remaining_time":0.005206676532},
{"learn":[3.054200234],"iteration":996,"passed_time":1.29742468,"remaining_time":0.003903985999},
{"learn":[3.052732869],"iteration":997,"passed_time":1.298413002,"remaining_time":0.002602030064},
{"learn":[3.051787862],"iteration":998,"passed_time":1.299416656,"remaining_time":0.001300717373},
{"learn":[3.051366222],"iteration":999,"passed_time":1.300369282,"remaining_time":0}
]}